{
  "question_id": "23.0",
  "language": "tc",
  "reference_documents": "GI000028 > PRUChoice Home Claims Seminar_2907 p. 13\nGI000028 > Training for Home_Maid_202309_clean_PIL p. 34-36\nGI000029 > 【GI通訊】狂雨淹港 家居車險商鋪辦公室可以點保.pdf p. 2\nGI000028 > GI Home Claims Training_20022023 p. 7-21\nGI000030 > pruchoice home insurance claim form_0923 > p.1-7",
  "reference_marker": null,
  "query": "如何就家居寶保提出索償?",
  "runs": [
    {
      "query": "如何就家居寶保提出索償?",
      "search_method": "vector",
      "total_result": 10,
      "results": [
        {
          "id": "GI000028",
          "document_id": "GI000028",
          "title_name_en": "GIEB Training Courses Material",
          "title_name_tc": "GIEB 培訓課程資料",
          "content_en": "●103\n索償個案分享\n一次\n答案\n受保人的索償內容如下:\n1. 第三者索償\n索償金額\n賠償金額\n窗\n5,000\n5,000\nConfidential\n103●104\n索償個案分享\n答案-2. 家居財物\n財物\n索償金額\n賠償金額\n音響設備(包括兩對喇叭)\n80,000\n75,000\n衣櫃\n5,000\n5,000\n衣物\n10,000\n8,000\n手錶\n20,000\n10,000\n牆紙\nNE\n10,000\n9,000\n受保人安裝的地板\n20,000\n20,000\n臨時居所租金\n5,000\n5,000\n總賠償金額\n132,000\n扣:自負額\n250\n淨賠償金額\n131,750\nConfidential\n104",
          "content_tc": "●103\n索償個案分享\n一次\n答案\n受保人的索償內容如下:\n1. 第三者索償\n索償金額\n賠償金額\n窗\n5,000\n5,000\nConfidential\n103●104\n索償個案分享\n答案-2. 家居財物\n財物\n索償金額\n賠償金額\n音響設備(包括兩對喇叭)\n80,000\n75,000\n衣櫃\n5,000\n5,000\n衣物\n10,000\n8,000\n手錶\n20,000\n10,000\n牆紙\nNE\n10,000\n9,000\n受保人安裝的地板\n20,000\n20,000\n臨時居所租金\n5,000\n5,000\n總賠償金額\n132,000\n扣:自負額\n250\n淨賠償金額\n131,750\nConfidential\n104",
          "filename": "Training for Home_Maid_202309_clean_PIL.pdf",
          "page_number": null,
          "score": 0.71509254,
          "content_chunk": "●103\n索償個案分享\n一次\n答案\n受保人的索償內容如下:\n1. 第三者索償\n索償金額\n賠償金額\n窗\n5,000\n5,000\nConfidential\n103●104\n索償個案分享\n答案-2. 家居財物\n財物\n索償金額\n賠償金額\n音響設備(包括兩對喇叭)\n80,000\n75,000\n衣櫃\n5,000\n5,000\n衣物\n10,000\n8,000\n手錶\n20,000\n10,000\n牆紙\nNE\n10,000\n9,000\n受保人安裝的地板\n20,000\n20,000\n臨時居所租金\n5,000\n5,000\n總賠償金額\n132,000\n扣:自負額\n250\n淨賠償金額\n131,750\nConfidential\n104"
        },
        {
          "id": "GI000028",
          "document_id": "GI000028",
          "title_name_en": "GIEB Training Courses Material",
          "title_name_tc": "GIEB 培訓課程資料",
          "content_en": "●101\n索償個案分享\n一次\n問題1.\n實際賠償金額是多少?\n受保人的索償內容如下:\n1. 第三者索償\n索償金額\n賠償金額\n窗\n5,000\n??\nConfidential\n101●102\n索償個案分享\nージ\n2. 家居財物\n財物\n索償金額\n賠償金額\n音響設備(包括兩對喇叭)\n80,000\n??\n衣櫃\n5,000\n??\n衣物\n10,000\n??\n手錶\n20,000\n??\n牆紙\n10,000\n??\n受保人安裝的地板\n20,000\n??\n臨時居所租金\n5,000\n??\n總賠償金額\n??\n扣:自負額\n??\n淨賠償金額\n??\nConfidential\n102",
          "content_tc": "●101\n索償個案分享\n一次\n問題1.\n實際賠償金額是多少?\n受保人的索償內容如下:\n1. 第三者索償\n索償金額\n賠償金額\n窗\n5,000\n??\nConfidential\n101●102\n索償個案分享\nージ\n2. 家居財物\n財物\n索償金額\n賠償金額\n音響設備(包括兩對喇叭)\n80,000\n??\n衣櫃\n5,000\n??\n衣物\n10,000\n??\n手錶\n20,000\n??\n牆紙\n10,000\n??\n受保人安裝的地板\n20,000\n??\n臨時居所租金\n5,000\n??\n總賠償金額\n??\n扣:自負額\n??\n淨賠償金額\n??\nConfidential\n102",
          "filename": "Training for Home_Maid_202309_clean_PIL.pdf",
          "page_number": null,
          "score": 0.712293,
          "content_chunk": "●101\n索償個案分享\n一次\n問題1.\n實際賠償金額是多少?\n受保人的索償內容如下:\n1. 第三者索償\n索償金額\n賠償金額\n窗\n5,000\n??\nConfidential\n101●102\n索償個案分享\nージ\n2. 家居財物\n財物\n索償金額\n賠償金額\n音響設備(包括兩對喇叭)\n80,000\n??\n衣櫃\n5,000\n??\n衣物\n10,000\n??\n手錶\n20,000\n??\n牆紙\n10,000\n??\n受保人安裝的地板\n20,000\n??\n臨時居所租金\n5,000\n??\n總賠償金額\n??\n扣:自負額\n??\n淨賠償金額\n??\nConfidential\n102"
        },
        {
          "id": "GI000028",
          "document_id": "GI000028",
          "title_name_en": "GIEB Training Courses Material",
          "title_name_tc": "GIEB 培訓課程資料",
          "content_en": "●104\n索償個案分享\n答案-2. 家居財物\n財物\n索償金額\n賠償金額\n音響設備(包括兩對喇叭)\n80,000\n75,000\n衣櫃\n5,000\n5,000\n衣物\n10,000\n8,000\n手錶\n20,000\n10,000\n牆紙\nNE\n10,000\n9,000\n受保人安裝的地板\n20,000\n20,000\n臨時居所租金\n5,000\n5,000\n總賠償金額\n132,000\n扣:自負額\n250\n淨賠償金額\n131,750\nConfidential\n104●105\n索償個案分享\n答案\n一次\n財物\n賠償金額\n原因\n音響設備(包括兩對喇叭)\n75,000\n每件最高限額\n衣櫃\n5,000\n衣物\n8,000\n扣除折舊\n手錶\n10,000\n每件最高限額\n牆紙\n9,000\n扣除自負金額\nHK$1,000\n受保人安裝的地板\n20,000\n臨時居所租金\n5,000\nConfidential\n105",
          "content_tc": "●104\n索償個案分享\n答案-2. 家居財物\n財物\n索償金額\n賠償金額\n音響設備(包括兩對喇叭)\n80,000\n75,000\n衣櫃\n5,000\n5,000\n衣物\n10,000\n8,000\n手錶\n20,000\n10,000\n牆紙\nNE\n10,000\n9,000\n受保人安裝的地板\n20,000\n20,000\n臨時居所租金\n5,000\n5,000\n總賠償金額\n132,000\n扣:自負額\n250\n淨賠償金額\n131,750\nConfidential\n104●105\n索償個案分享\n答案\n一次\n財物\n賠償金額\n原因\n音響設備(包括兩對喇叭)\n75,000\n每件最高限額\n衣櫃\n5,000\n衣物\n8,000\n扣除折舊\n手錶\n10,000\n每件最高限額\n牆紙\n9,000\n扣除自負金額\nHK$1,000\n受保人安裝的地板\n20,000\n臨時居所租金\n5,000\nConfidential\n105",
          "filename": "Training for Home_Maid_202309_clean_PIL.pdf",
          "page_number": null,
          "score": 0.7100719,
          "content_chunk": "●104\n索償個案分享\n答案-2. 家居財物\n財物\n索償金額\n賠償金額\n音響設備(包括兩對喇叭)\n80,000\n75,000\n衣櫃\n5,000\n5,000\n衣物\n10,000\n8,000\n手錶\n20,000\n10,000\n牆紙\nNE\n10,000\n9,000\n受保人安裝的地板\n20,000\n20,000\n臨時居所租金\n5,000\n5,000\n總賠償金額\n132,000\n扣:自負額\n250\n淨賠償金額\n131,750\nConfidential\n104●105\n索償個案分享\n答案\n一次\n財物\n賠償金額\n原因\n音響設備(包括兩對喇叭)\n75,000\n每件最高限額\n衣櫃\n5,000\n衣物\n8,000\n扣除折舊\n手錶\n10,000\n每件最高限額\n牆紙\n9,000\n扣除自負金額\nHK$1,000\n受保人安裝的地板\n20,000\n臨時居所租金\n5,000\nConfidential\n105"
        },
        {
          "id": "GI000028",
          "document_id": "GI000028",
          "title_name_en": "GIEB Training Courses Material",
          "title_name_tc": "GIEB 培訓課程資料",
          "content_en": "●102\n索償個案分享\nージ\n2. 家居財物\n財物\n索償金額\n賠償金額\n音響設備(包括兩對喇叭)\n80,000\n??\n衣櫃\n5,000\n??\n衣物\n10,000\n??\n手錶\n20,000\n??\n牆紙\n10,000\n??\n受保人安裝的地板\n20,000\n??\n臨時居所租金\n5,000\n??\n總賠償金額\n??\n扣:自負額\n??\n淨賠償金額\n??\nConfidential\n102●103\n索償個案分享\n一次\n答案\n受保人的索償內容如下:\n1. 第三者索償\n索償金額\n賠償金額\n窗\n5,000\n5,000\nConfidential\n103",
          "content_tc": "●102\n索償個案分享\nージ\n2. 家居財物\n財物\n索償金額\n賠償金額\n音響設備(包括兩對喇叭)\n80,000\n??\n衣櫃\n5,000\n??\n衣物\n10,000\n??\n手錶\n20,000\n??\n牆紙\n10,000\n??\n受保人安裝的地板\n20,000\n??\n臨時居所租金\n5,000\n??\n總賠償金額\n??\n扣:自負額\n??\n淨賠償金額\n??\nConfidential\n102●103\n索償個案分享\n一次\n答案\n受保人的索償內容如下:\n1. 第三者索償\n索償金額\n賠償金額\n窗\n5,000\n5,000\nConfidential\n103",
          "filename": "Training for Home_Maid_202309_clean_PIL.pdf",
          "page_number": null,
          "score": 0.7036883,
          "content_chunk": "●102\n索償個案分享\nージ\n2. 家居財物\n財物\n索償金額\n賠償金額\n音響設備(包括兩對喇叭)\n80,000\n??\n衣櫃\n5,000\n??\n衣物\n10,000\n??\n手錶\n20,000\n??\n牆紙\n10,000\n??\n受保人安裝的地板\n20,000\n??\n臨時居所租金\n5,000\n??\n總賠償金額\n??\n扣:自負額\n??\n淨賠償金額\n??\nConfidential\n102●103\n索償個案分享\n一次\n答案\n受保人的索償內容如下:\n1. 第三者索償\n索償金額\n賠償金額\n窗\n5,000\n5,000\nConfidential\n103"
        },
        {
          "id": "GI000028",
          "document_id": "GI000028",
          "title_name_en": "GIEB Training Courses Material",
          "title_name_tc": "GIEB 培訓課程資料",
          "content_en": "●156\n索償注意事項\n一次\n保誠精選「僱傭寶」\n常見索償\n-門診費用(94%)\n常見不獲賠償項目\n- 發生在免責期內的醫療事故(23%)\n- 身體檢查或疫苗注射(22%)\nConfidential\n156●157\n索償注意事項\n一次\n保誠精選「僱傭寶」- 索償所需文件\n僱員賠償\n- 勞工處的表格2/表格2B副本\n- 病假證明書及醫療費用收據正本\n-倘若適用,呈交評估證明書(表格5,7或9)正本\n門診費用及住院和手術費用及牙醫費用\n-列明註冊醫生診斷的醫療費/住院帳單/收據正本\n簡易門診索償程序\n您只需要於附有外籍家庭傭工姓名、病況及診金的正本醫療收\n據背頁寫上有關保單號碼,並將收據交予閣下的理財顧問或寄\n至保誠財險有限公司(香港鯛魚涌華蘭路25號柏克大廈3樓)\n即可。有關其他索償條件,請參閱保單。\nConfidential\n157",
          "content_tc": "●156\n索償注意事項\n一次\n保誠精選「僱傭寶」\n常見索償\n-門診費用(94%)\n常見不獲賠償項目\n- 發生在免責期內的醫療事故(23%)\n- 身體檢查或疫苗注射(22%)\nConfidential\n156●157\n索償注意事項\n一次\n保誠精選「僱傭寶」- 索償所需文件\n僱員賠償\n- 勞工處的表格2/表格2B副本\n- 病假證明書及醫療費用收據正本\n-倘若適用,呈交評估證明書(表格5,7或9)正本\n門診費用及住院和手術費用及牙醫費用\n-列明註冊醫生診斷的醫療費/住院帳單/收據正本\n簡易門診索償程序\n您只需要於附有外籍家庭傭工姓名、病況及診金的正本醫療收\n據背頁寫上有關保單號碼,並將收據交予閣下的理財顧問或寄\n至保誠財險有限公司(香港鯛魚涌華蘭路25號柏克大廈3樓)\n即可。有關其他索償條件,請參閱保單。\nConfidential\n157",
          "filename": "Training for Home_Maid_202309_clean_PIL.pdf",
          "page_number": null,
          "score": 0.7018477,
          "content_chunk": "●156\n索償注意事項\n一次\n保誠精選「僱傭寶」\n常見索償\n-門診費用(94%)\n常見不獲賠償項目\n- 發生在免責期內的醫療事故(23%)\n- 身體檢查或疫苗注射(22%)\nConfidential\n156●157\n索償注意事項\n一次\n保誠精選「僱傭寶」- 索償所需文件\n僱員賠償\n- 勞工處的表格2/表格2B副本\n- 病假證明書及醫療費用收據正本\n-倘若適用,呈交評估證明書(表格5,7或9)正本\n門診費用及住院和手術費用及牙醫費用\n-列明註冊醫生診斷的醫療費/住院帳單/收據正本\n簡易門診索償程序\n您只需要於附有外籍家庭傭工姓名、病況及診金的正本醫療收\n據背頁寫上有關保單號碼,並將收據交予閣下的理財顧問或寄\n至保誠財險有限公司(香港鯛魚涌華蘭路25號柏克大廈3樓)\n即可。有關其他索償條件,請參閱保單。\nConfidential\n157"
        },
        {
          "id": "GI000028",
          "document_id": "GI000028",
          "title_name_en": "GIEB Training Courses Material",
          "title_name_tc": "GIEB 培訓課程資料",
          "content_en": "●100\n索償個案分享\n一次\n個案二\n受保傭工忘記關掉暖爐,以致受保單位及其下單位\n受到破壞,而且投保人及傭工亦因此而受傷。\n(投保了小康之家)\nConfidential\n100●101\n索償個案分享\n一次\n問題1.\n實際賠償金額是多少?\n受保人的索償內容如下:\n1. 第三者索償\n索償金額\n賠償金額\n窗\n5,000\n??\nConfidential\n101",
          "content_tc": "●100\n索償個案分享\n一次\n個案二\n受保傭工忘記關掉暖爐,以致受保單位及其下單位\n受到破壞,而且投保人及傭工亦因此而受傷。\n(投保了小康之家)\nConfidential\n100●101\n索償個案分享\n一次\n問題1.\n實際賠償金額是多少?\n受保人的索償內容如下:\n1. 第三者索償\n索償金額\n賠償金額\n窗\n5,000\n??\nConfidential\n101",
          "filename": "Training for Home_Maid_202309_clean_PIL.pdf",
          "page_number": null,
          "score": 0.69797045,
          "content_chunk": "●100\n索償個案分享\n一次\n個案二\n受保傭工忘記關掉暖爐,以致受保單位及其下單位\n受到破壞,而且投保人及傭工亦因此而受傷。\n(投保了小康之家)\nConfidential\n100●101\n索償個案分享\n一次\n問題1.\n實際賠償金額是多少?\n受保人的索償內容如下:\n1. 第三者索償\n索償金額\n賠償金額\n窗\n5,000\n??\nConfidential\n101"
        },
        {
          "id": "GI000028",
          "document_id": "GI000028",
          "title_name_en": "GIEB Training Courses Material",
          "title_name_tc": "GIEB 培訓課程資料",
          "content_en": "●134\n計劃特點\n「僱員補償」一項中,額外支付家庭\n傭工在首12個月暫時喪失工作能力期\n間的每月100%收入\n在僱員補償條例下,僱主只需支\n付80%的每月收入給您的家庭傭工\n在保誠精選「僱傭寶」,僱主可支\n付100%的每月收入給您的家庭傭工\nConfidential\n134●135\n保障一覽\n一次\n最高賠償額\n(港幣$)\n3. 忠誠保障\n年6,000\n補償您因家庭傭工的欺詐或不誠實的行為而引\n致的經濟損失。\n更換大門鎖及大閘鎖額外保障:\n每年1,000\n如您在「忠誠保障」下作出了有效的索償,當\n您因家庭傭工的向放債人借錢後無故失蹤,欺\n詐或不誠實的行為而終止其僱傭合約時,我們\n亦會支付您因此而需要更換及安裝大門鎖和大\n閘鎖所實際產生的費用。惟有關更換及安裝工\n作須於終止家庭傭工的僱傭合約14天內進\n行。\nConfidential\n135",
          "content_tc": "●134\n計劃特點\n「僱員補償」一項中,額外支付家庭\n傭工在首12個月暫時喪失工作能力期\n間的每月100%收入\n在僱員補償條例下,僱主只需支\n付80%的每月收入給您的家庭傭工\n在保誠精選「僱傭寶」,僱主可支\n付100%的每月收入給您的家庭傭工\nConfidential\n134●135\n保障一覽\n一次\n最高賠償額\n(港幣$)\n3. 忠誠保障\n年6,000\n補償您因家庭傭工的欺詐或不誠實的行為而引\n致的經濟損失。\n更換大門鎖及大閘鎖額外保障:\n每年1,000\n如您在「忠誠保障」下作出了有效的索償,當\n您因家庭傭工的向放債人借錢後無故失蹤,欺\n詐或不誠實的行為而終止其僱傭合約時,我們\n亦會支付您因此而需要更換及安裝大門鎖和大\n閘鎖所實際產生的費用。惟有關更換及安裝工\n作須於終止家庭傭工的僱傭合約14天內進\n行。\nConfidential\n135",
          "filename": "Training for Home_Maid_202309_clean_PIL.pdf",
          "page_number": null,
          "score": 0.6967084,
          "content_chunk": "●134\n計劃特點\n「僱員補償」一項中,額外支付家庭\n傭工在首12個月暫時喪失工作能力期\n間的每月100%收入\n在僱員補償條例下,僱主只需支\n付80%的每月收入給您的家庭傭工\n在保誠精選「僱傭寶」,僱主可支\n付100%的每月收入給您的家庭傭工\nConfidential\n134●135\n保障一覽\n一次\n最高賠償額\n(港幣$)\n3. 忠誠保障\n年6,000\n補償您因家庭傭工的欺詐或不誠實的行為而引\n致的經濟損失。\n更換大門鎖及大閘鎖額外保障:\n每年1,000\n如您在「忠誠保障」下作出了有效的索償,當\n您因家庭傭工的向放債人借錢後無故失蹤,欺\n詐或不誠實的行為而終止其僱傭合約時,我們\n亦會支付您因此而需要更換及安裝大門鎖和大\n閘鎖所實際產生的費用。惟有關更換及安裝工\n作須於終止家庭傭工的僱傭合約14天內進\n行。\nConfidential\n135"
        },
        {
          "id": "GI000028",
          "document_id": "GI000028",
          "title_name_en": "GIEB Training Courses Material",
          "title_name_tc": "GIEB 培訓課程資料",
          "content_en": "●99\n索償個案分享\n一次\n如在事故當地24小時內報警,賠償方案如下:\n- 現金\n損失時在香港,在(3)遺失現金保障內賠償\n- 手提包\n→ 在(2)全球個人財物保障內賠償\n- 銀包\n- iPad\n在(2)全球個人財物保障內賠償\n- 相機\n- 身份證\n→ 在(4)遺失個人證明文件保障內賠償\n→\n在(2)全球個人財物保障內賠償\n→\n在(2)全球個人財物保障內賠償\nConfidential\n99●100\n索償個案分享\n一次\n個案二\n受保傭工忘記關掉暖爐,以致受保單位及其下單位\n受到破壞,而且投保人及傭工亦因此而受傷。\n(投保了小康之家)\nConfidential\n100",
          "content_tc": "●99\n索償個案分享\n一次\n如在事故當地24小時內報警,賠償方案如下:\n- 現金\n損失時在香港,在(3)遺失現金保障內賠償\n- 手提包\n→ 在(2)全球個人財物保障內賠償\n- 銀包\n- iPad\n在(2)全球個人財物保障內賠償\n- 相機\n- 身份證\n→ 在(4)遺失個人證明文件保障內賠償\n→\n在(2)全球個人財物保障內賠償\n→\n在(2)全球個人財物保障內賠償\nConfidential\n99●100\n索償個案分享\n一次\n個案二\n受保傭工忘記關掉暖爐,以致受保單位及其下單位\n受到破壞,而且投保人及傭工亦因此而受傷。\n(投保了小康之家)\nConfidential\n100",
          "filename": "Training for Home_Maid_202309_clean_PIL.pdf",
          "page_number": null,
          "score": 0.6959542,
          "content_chunk": "●99\n索償個案分享\n一次\n如在事故當地24小時內報警,賠償方案如下:\n- 現金\n損失時在香港,在(3)遺失現金保障內賠償\n- 手提包\n→ 在(2)全球個人財物保障內賠償\n- 銀包\n- iPad\n在(2)全球個人財物保障內賠償\n- 相機\n- 身份證\n→ 在(4)遺失個人證明文件保障內賠償\n→\n在(2)全球個人財物保障內賠償\n→\n在(2)全球個人財物保障內賠償\nConfidential\n99●100\n索償個案分享\n一次\n個案二\n受保傭工忘記關掉暖爐,以致受保單位及其下單位\n受到破壞,而且投保人及傭工亦因此而受傷。\n(投保了小康之家)\nConfidential\n100"
        },
        {
          "id": "GI000064",
          "document_id": "GI000064",
          "title_name_en": "PRUchoice Maid",
          "title_name_tc": "保誠精選「僱傭寶」",
          "content_en": "保誠精選「僱傭寶」產品天書\n14. 索償\n客戶可經 eClaims申請索償。\n$\n•\n只需經手機或電腦登記及登入myPrudential,在\n發生事故後的31天內,上載數份所需索償表格\n及文件,就能申請電子索償,不但隨時隨地查閱\n索償狀態,日後更可輕鬆查閱保單詳情。\n版本:2021年12月30日保誠精選「僱傭寶」產品天書\n14. 索償\n一次\n14.2 索償所需文件 *:\n僱員補償\n□ 勞工處的表格2/表格2B副本\n病假證明書及醫療費用收據正本\n倘若適用,呈交評估證明書(表格5,7或9)正本\n門診費用及住院和手術費用及牙醫費用\n□ 列明註冊醫生診斷的醫療費/住院帳單/收據正本\n家庭成員被虐保障\n警方報告\n□警方調查報告以證明外籍家庭傭工的過失\n醫療報告\n*表格2B-僱主呈報引致僱員喪失工作能力不超過三天的意外的通知\n表格2-僱主呈報僱員死亡或引致僱員死亡或喪失工作能力的意外的通知\n表格5-補償評估證明書\n表格7-評估證明書\n表格9–覆檢評估證明書\nConfidential 36\n版本:2021年12月30日",
          "content_tc": "保誠精選「僱傭寶」產品天書\n14. 索償\n客戶可經 eClaims申請索償。\n$\n•\n只需經手機或電腦登記及登入myPrudential,在\n發生事故後的31天內,上載數份所需索償表格\n及文件,就能申請電子索償,不但隨時隨地查閱\n索償狀態,日後更可輕鬆查閱保單詳情。\n版本:2021年12月30日保誠精選「僱傭寶」產品天書\n14. 索償\n一次\n14.2 索償所需文件 *:\n僱員補償\n□ 勞工處的表格2/表格2B副本\n病假證明書及醫療費用收據正本\n倘若適用,呈交評估證明書(表格5,7或9)正本\n門診費用及住院和手術費用及牙醫費用\n□ 列明註冊醫生診斷的醫療費/住院帳單/收據正本\n家庭成員被虐保障\n警方報告\n□警方調查報告以證明外籍家庭傭工的過失\n醫療報告\n*表格2B-僱主呈報引致僱員喪失工作能力不超過三天的意外的通知\n表格2-僱主呈報僱員死亡或引致僱員死亡或喪失工作能力的意外的通知\n表格5-補償評估證明書\n表格7-評估證明書\n表格9–覆檢評估證明書\nConfidential 36\n版本:2021年12月30日",
          "filename": "Maid Sales Toolkit_30122021.pdf",
          "page_number": null,
          "score": 0.69026875,
          "content_chunk": "保誠精選「僱傭寶」產品天書\n14. 索償\n客戶可經 eClaims申請索償。\n$\n•\n只需經手機或電腦登記及登入myPrudential,在\n發生事故後的31天內,上載數份所需索償表格\n及文件,就能申請電子索償,不但隨時隨地查閱\n索償狀態,日後更可輕鬆查閱保單詳情。\n版本:2021年12月30日保誠精選「僱傭寶」產品天書\n14. 索償\n一次\n14.2 索償所需文件 *:\n僱員補償\n□ 勞工處的表格2/表格2B副本\n病假證明書及醫療費用收據正本\n倘若適用,呈交評估證明書(表格5,7或9)正本\n門診費用及住院和手術費用及牙醫費用\n□ 列明註冊醫生診斷的醫療費/住院帳單/收據正本\n家庭成員被虐保障\n警方報告\n□警方調查報告以證明外籍家庭傭工的過失\n醫療報告\n*表格2B-僱主呈報引致僱員喪失工作能力不超過三天的意外的通知\n表格2-僱主呈報僱員死亡或引致僱員死亡或喪失工作能力的意外的通知\n表格5-補償評估證明書\n表格7-評估證明書\n表格9–覆檢評估證明書\nConfidential 36\n版本:2021年12月30日"
        },
        {
          "id": "GI000028",
          "document_id": "GI000028",
          "title_name_en": "GIEB Training Courses Material",
          "title_name_tc": "GIEB 培訓課程資料",
          "content_en": "●155\n索償注意事項●156\n索償注意事項\n一次\n保誠精選「僱傭寶」\n常見索償\n-門診費用(94%)\n常見不獲賠償項目\n- 發生在免責期內的醫療事故(23%)\n- 身體檢查或疫苗注射(22%)\nConfidential\n156",
          "content_tc": "●155\n索償注意事項●156\n索償注意事項\n一次\n保誠精選「僱傭寶」\n常見索償\n-門診費用(94%)\n常見不獲賠償項目\n- 發生在免責期內的醫療事故(23%)\n- 身體檢查或疫苗注射(22%)\nConfidential\n156",
          "filename": "Training for Home_Maid_202309_clean_PIL.pdf",
          "page_number": null,
          "score": 0.6892217,
          "content_chunk": "●155\n索償注意事項●156\n索償注意事項\n一次\n保誠精選「僱傭寶」\n常見索償\n-門診費用(94%)\n常見不獲賠償項目\n- 發生在免責期內的醫療事故(23%)\n- 身體檢查或疫苗注射(22%)\nConfidential\n156"
        }
      ]
    },
    {
      "query": "如何就家居寶保提出索償?",
      "search_method": "hybrid",
      "total_result": 10,
      "results": [
        {
          "id": "GI000061",
          "document_id": "GI000061",
          "title_name_en": "PRUchoice Home",
          "title_name_tc": "保誠精選「家居寶」",
          "content_en": "保誠精選「家居寶」2022\n12. 索償\n12.1 客戶可經 eClaims申請索償。\n$\n· 只需經手機或電腦登記及登入myPrudential,在\n發生事故後的31天內,上載數份所需索償表格\n及文件,就能申請電子索償,不但隨時隨地查閱\n索償狀態,日後更可輕鬆查閱保單詳情。\nConfidential\n41\n此為機密文件,及只作內部業務用途。請勿轉發。\n請注意:整個銷售過程及所有申請程序必須在香港進行保誠精選「家居寶」2022\n12. 索償\n12.2 索償項目\n12.2.1 家居財物/個人財物失竊保障\n■ 必須於發現後二十四小時內向警方報告\n■ 日常隨身攜帶的個人財物,不應無人看管,否則該損失可能不獲保障\n■ 請保存原有配件、使用指南、說明書及保證書,並在有需要時提供作檢\n查之用,直至索償完成\n■ 手提電話/任何具手提電話功能的電子產品,及其所有配件均不受保障\n12.2.2 滲水至第三者單單位情況\n▪\n在滲水出現時,就受保人可能需要負上的法律責任,即因疏忽而導致第\n三者損失,作出處理及賠償\n■ 當發現滲水,不論第三者有否追討賠償,受保人都應立即填寫索償表格\n並交予我們作通知,在得悉有關情況後,我們將為賠償事宜作出考慮與\n安排\n■ 受保人應立即找出滲水的源頭,及在有需要時安排維修人員維修\n■ 如收到索償信、律師信或法庭傳票等,請勿私自回覆,並應立即交予我\n們\n■ 請勿私自向任何第三者承認責任或作出賠償承諾\n■ 如第三者向受保人追討賠償,請要求第三者以書面形式列明其要求。當\n受保人收到第三者的書面索償,請立即交予我們。如有需要,我們將直\n接聯絡第三者\n12.2.3 遺失現金及信用卡被盜用保障\n■ 若遺失信用卡,請即通知信用卡發行機構\n■ 必須於發現後二十四小時內向警方報告\nConfidential 42\n此為機密文件,及只作內部業務用途。請勿轉發。\n請注意:整個銷售過程及所有申請程序必須在香港進行",
          "content_tc": "保誠精選「家居寶」2022\n12. 索償\n12.1 客戶可經 eClaims申請索償。\n$\n· 只需經手機或電腦登記及登入myPrudential,在\n發生事故後的31天內,上載數份所需索償表格\n及文件,就能申請電子索償,不但隨時隨地查閱\n索償狀態,日後更可輕鬆查閱保單詳情。\nConfidential\n41\n此為機密文件,及只作內部業務用途。請勿轉發。\n請注意:整個銷售過程及所有申請程序必須在香港進行保誠精選「家居寶」2022\n12. 索償\n12.2 索償項目\n12.2.1 家居財物/個人財物失竊保障\n■ 必須於發現後二十四小時內向警方報告\n■ 日常隨身攜帶的個人財物,不應無人看管,否則該損失可能不獲保障\n■ 請保存原有配件、使用指南、說明書及保證書,並在有需要時提供作檢\n查之用,直至索償完成\n■ 手提電話/任何具手提電話功能的電子產品,及其所有配件均不受保障\n12.2.2 滲水至第三者單單位情況\n▪\n在滲水出現時,就受保人可能需要負上的法律責任,即因疏忽而導致第\n三者損失,作出處理及賠償\n■ 當發現滲水,不論第三者有否追討賠償,受保人都應立即填寫索償表格\n並交予我們作通知,在得悉有關情況後,我們將為賠償事宜作出考慮與\n安排\n■ 受保人應立即找出滲水的源頭,及在有需要時安排維修人員維修\n■ 如收到索償信、律師信或法庭傳票等,請勿私自回覆,並應立即交予我\n們\n■ 請勿私自向任何第三者承認責任或作出賠償承諾\n■ 如第三者向受保人追討賠償,請要求第三者以書面形式列明其要求。當\n受保人收到第三者的書面索償,請立即交予我們。如有需要,我們將直\n接聯絡第三者\n12.2.3 遺失現金及信用卡被盜用保障\n■ 若遺失信用卡,請即通知信用卡發行機構\n■ 必須於發現後二十四小時內向警方報告\nConfidential 42\n此為機密文件,及只作內部業務用途。請勿轉發。\n請注意:整個銷售過程及所有申請程序必須在香港進行",
          "filename": "Home_Sales Toolkit_26 April 2022.pdf",
          "page_number": null,
          "score": 0.028991596773266792,
          "content_chunk": "保誠精選「家居寶」2022\n12. 索償\n12.1 客戶可經 eClaims申請索償。\n$\n· 只需經手機或電腦登記及登入myPrudential,在\n發生事故後的31天內,上載數份所需索償表格\n及文件,就能申請電子索償,不但隨時隨地查閱\n索償狀態,日後更可輕鬆查閱保單詳情。\nConfidential\n41\n此為機密文件,及只作內部業務用途。請勿轉發。\n請注意:整個銷售過程及所有申請程序必須在香港進行保誠精選「家居寶」2022\n12. 索償\n12.2 索償項目\n12.2.1 家居財物/個人財物失竊保障\n■ 必須於發現後二十四小時內向警方報告\n■ 日常隨身攜帶的個人財物,不應無人看管,否則該損失可能不獲保障\n■ 請保存原有配件、使用指南、說明書及保證書,並在有需要時提供作檢\n查之用,直至索償完成\n■ 手提電話/任何具手提電話功能的電子產品,及其所有配件均不受保障\n12.2.2 滲水至第三者單單位情況\n▪\n在滲水出現時,就受保人可能需要負上的法律責任,即因疏忽而導致第\n三者損失,作出處理及賠償\n■ 當發現滲水,不論第三者有否追討賠償,受保人都應立即填寫索償表格\n並交予我們作通知,在得悉有關情況後,我們將為賠償事宜作出考慮與\n安排\n■ 受保人應立即找出滲水的源頭,及在有需要時安排維修人員維修\n■ 如收到索償信、律師信或法庭傳票等,請勿私自回覆,並應立即交予我\n們\n■ 請勿私自向任何第三者承認責任或作出賠償承諾\n■ 如第三者向受保人追討賠償,請要求第三者以書面形式列明其要求。當\n受保人收到第三者的書面索償,請立即交予我們。如有需要,我們將直\n接聯絡第三者\n12.2.3 遺失現金及信用卡被盜用保障\n■ 若遺失信用卡,請即通知信用卡發行機構\n■ 必須於發現後二十四小時內向警方報告\nConfidential 42\n此為機密文件,及只作內部業務用途。請勿轉發。\n請注意:整個銷售過程及所有申請程序必須在香港進行"
        },
        {
          "id": "GI000061",
          "document_id": "GI000061",
          "title_name_en": "PRUchoice Home",
          "title_name_tc": "保誠精選「家居寶」",
          "content_en": "保誠精選「家居寶」2022\n5. 保障範圍快覽\n基本保障\n5. 第三者法律責任保障\n•\n保障客戶及客戶的家人在下列情況,因疏忽而導致第三\n者身體受傷或財物損失,而需負上的法律責任。\n✓\n身為受保住所的住戶\n✓\n以個人身份,在香港或前往海外暫時停留\n飼養家居寵物\n✓\n✓\n外籍家庭傭工/本地家務助理為您從事家務工作時\n,因疏忽而導致第三者身體受傷或財物損失,而您\n作為僱主的責任\n額外保障\n5.1 業主法律責任保障\nS\n•\n額外保障客戶作為業主,因住所或大廈公眾地方發生意外,\n疏忽導致第三者身體受傷或財物損失時,所需負上的法律責\n任。\n+\n5.2 鄰居單位水濕保障\n•\n在無論過失的情況下,我們額外保障因客戶住所引致第三者\n財產意外水濕損毀(不論過失)而產生的合理維修費用。\nConfidential\n12\n此為機密文件,及只作內部業務用途。請勿轉發。\n請注意:整個銷售過程及所有申請程序必須在香港進行保誠精選「家居寶」2022\n5. 保障範圍快覽\n基本保障\n6. 家居意外保障\n•\n若因家居火災、持械行劫或盜竊,導致客戶及客戶的家\n人身亡、完全永久傷殘、喪失肢體或喪失視力,將獲得\n賠償。\n額外保障\n6.1 火災/行劫/盜竊的受傷津貼\n•\n客戶或客戶的家人,因家居火災、持械行劫或盜竊而受\n傷,我們會支付所需的醫療費用。\n7. 新居過渡期保障\n•\n在得悉客戶搬遷消息後,我們將於客戶首次佔用該新住所\n時起計,就新住所免費提供項目1-家居財物保障及項目5\n–第三者法律責任保障,保障期為兩星期。\nConfidential\n13\n此為機密文件,及只作內部業務用途。請勿轉發。\n請注意:整個銷售過程及所有申請程序必須在香港進行",
          "content_tc": "保誠精選「家居寶」2022\n5. 保障範圍快覽\n基本保障\n5. 第三者法律責任保障\n•\n保障客戶及客戶的家人在下列情況,因疏忽而導致第三\n者身體受傷或財物損失,而需負上的法律責任。\n✓\n身為受保住所的住戶\n✓\n以個人身份,在香港或前往海外暫時停留\n飼養家居寵物\n✓\n✓\n外籍家庭傭工/本地家務助理為您從事家務工作時\n,因疏忽而導致第三者身體受傷或財物損失,而您\n作為僱主的責任\n額外保障\n5.1 業主法律責任保障\nS\n•\n額外保障客戶作為業主,因住所或大廈公眾地方發生意外,\n疏忽導致第三者身體受傷或財物損失時,所需負上的法律責\n任。\n+\n5.2 鄰居單位水濕保障\n•\n在無論過失的情況下,我們額外保障因客戶住所引致第三者\n財產意外水濕損毀(不論過失)而產生的合理維修費用。\nConfidential\n12\n此為機密文件,及只作內部業務用途。請勿轉發。\n請注意:整個銷售過程及所有申請程序必須在香港進行保誠精選「家居寶」2022\n5. 保障範圍快覽\n基本保障\n6. 家居意外保障\n•\n若因家居火災、持械行劫或盜竊,導致客戶及客戶的家\n人身亡、完全永久傷殘、喪失肢體或喪失視力,將獲得\n賠償。\n額外保障\n6.1 火災/行劫/盜竊的受傷津貼\n•\n客戶或客戶的家人,因家居火災、持械行劫或盜竊而受\n傷,我們會支付所需的醫療費用。\n7. 新居過渡期保障\n•\n在得悉客戶搬遷消息後,我們將於客戶首次佔用該新住所\n時起計,就新住所免費提供項目1-家居財物保障及項目5\n–第三者法律責任保障,保障期為兩星期。\nConfidential\n13\n此為機密文件,及只作內部業務用途。請勿轉發。\n請注意:整個銷售過程及所有申請程序必須在香港進行",
          "filename": "Home_Sales Toolkit_26 April 2022.pdf",
          "page_number": null,
          "score": 0.02422296814620495,
          "content_chunk": "保誠精選「家居寶」2022\n5. 保障範圍快覽\n基本保障\n5. 第三者法律責任保障\n•\n保障客戶及客戶的家人在下列情況,因疏忽而導致第三\n者身體受傷或財物損失,而需負上的法律責任。\n✓\n身為受保住所的住戶\n✓\n以個人身份,在香港或前往海外暫時停留\n飼養家居寵物\n✓\n✓\n外籍家庭傭工/本地家務助理為您從事家務工作時\n,因疏忽而導致第三者身體受傷或財物損失,而您\n作為僱主的責任\n額外保障\n5.1 業主法律責任保障\nS\n•\n額外保障客戶作為業主,因住所或大廈公眾地方發生意外,\n疏忽導致第三者身體受傷或財物損失時,所需負上的法律責\n任。\n+\n5.2 鄰居單位水濕保障\n•\n在無論過失的情況下,我們額外保障因客戶住所引致第三者\n財產意外水濕損毀(不論過失)而產生的合理維修費用。\nConfidential\n12\n此為機密文件,及只作內部業務用途。請勿轉發。\n請注意:整個銷售過程及所有申請程序必須在香港進行保誠精選「家居寶」2022\n5. 保障範圍快覽\n基本保障\n6. 家居意外保障\n•\n若因家居火災、持械行劫或盜竊,導致客戶及客戶的家\n人身亡、完全永久傷殘、喪失肢體或喪失視力,將獲得\n賠償。\n額外保障\n6.1 火災/行劫/盜竊的受傷津貼\n•\n客戶或客戶的家人,因家居火災、持械行劫或盜竊而受\n傷,我們會支付所需的醫療費用。\n7. 新居過渡期保障\n•\n在得悉客戶搬遷消息後,我們將於客戶首次佔用該新住所\n時起計,就新住所免費提供項目1-家居財物保障及項目5\n–第三者法律責任保障,保障期為兩星期。\nConfidential\n13\n此為機密文件,及只作內部業務用途。請勿轉發。\n請注意:整個銷售過程及所有申請程序必須在香港進行"
        },
        {
          "id": "GI000063",
          "document_id": "GI000063",
          "title_name_en": "PRUchoice Home Landlord",
          "title_name_tc": "保誠精選「業主寶」",
          "content_en": "保誠精選「業主寶」2022\n12. 索償\n12.1 客戶可經 eClaims申請索償。\n$\n· 只需經手機或電腦登記及登入myPrudential,在\n發生事故後的31天內,上載數份所需索償表格\n及文件,就能申請電子索償,不但隨時隨地查閱\n索償狀態,日後更可輕鬆查閱保單詳情。\nConfidential\n36\n此為機密文件,及只作內部業務用途。請勿轉發。\n請注意:整個銷售過程及所有申請程序必須在香港進行保誠精選「業主寶」2022\n12. 索償\n12.2 索償項目\n12.2.1 家居財物/個人財物失竊保障\n■ 就家居財物損毀作出賠償,惟不包括樓宇部分、固定裝置及配置(除非是\n由受保人自行添置的室內裝修,詳情請參考下列註釋)\n■ 家居財物的損毀,應由意外性質事件所導致。因此,若因1. 自然損耗2.蛀\n蟲3. 害蟲4. 昆蟲5. 寵物6. 潮濕7.生鏽8.腐爛9. 腐蝕10. 發霉11. 濕氣12.陽\n光或大氣作用及13.以漸進原因所導致或促成的損毀,是不獲保障的\n■ 當意外性質事件發生時,應立即阻止,減低損失\n■ 因電力或機械故障、錯亂、負荷過多或不足所導致的電器損毀是不獲保障\n的\n■ 玻璃物件(包括鏡、陶瓷器、陶器、土器及水晶擺設)因火災、爆炸、爆\n竊或盜竊而被打碎是獲保障的\n■ 若室內裝修、固定裝置及配置由受保人自行添置,皆可被視作家居財物。\n請提供自行添置這些室內裝修、固定裝置及配置的證明,例如原有安裝收\n據正本等。否則,這些物件將被視作樓宇一部分,並只會在保單中另有投\n保樓宇結構保障項目的情況下受保\n不保障手提電話損毀,除非受保人已支付額外保費,特別為該手提電話投\n保\n■\n任何於清潔、修改、維修、翻新、保養或漂染過程中,或錯誤使用、違反\n製造商指引下使用、內在缺陷、物料、圖樣或規格上的設計錯誤、或逐漸\n變壞及變型等所導致的損毀是不受保障的\n12.2.2 滲水至第三者單單位情況\n■ 在滲水出現時,就受保人可能需要負上的法律責任,即因疏忽而導致第三\n者損失,作出處理及賠償\n■ 當發現滲水,不論第三者有否追討賠償,受保人都應立即填寫索償表格並\n交予我們作通知,在得悉有關情況後,我們將為賠償事宜作出考慮與安排\n■ 受保人應立即找出滲水的源頭,及在有需要時安排維修人員維修\n■ 如收到索償信、律師信或法庭傳票等,請勿私自回覆,並應立即交予我們\n■ 請勿私自向任何第三者承認責任或作出賠償承諾\n■ 如第三者向受保人追討賠償,請要求第三者以書面形式列明其要求。當受\n保人收到第三者的書面索償,請立即交予我們。如有需要,我們將直接聯\n絡第三者\nConfidential 37\n此為機密文件,及只作內部業務用途。請勿轉發。\n請注意:整個銷售過程及所有申請程序必須在香港進行",
          "content_tc": "保誠精選「業主寶」2022\n12. 索償\n12.1 客戶可經 eClaims申請索償。\n$\n· 只需經手機或電腦登記及登入myPrudential,在\n發生事故後的31天內,上載數份所需索償表格\n及文件,就能申請電子索償,不但隨時隨地查閱\n索償狀態,日後更可輕鬆查閱保單詳情。\nConfidential\n36\n此為機密文件,及只作內部業務用途。請勿轉發。\n請注意:整個銷售過程及所有申請程序必須在香港進行保誠精選「業主寶」2022\n12. 索償\n12.2 索償項目\n12.2.1 家居財物/個人財物失竊保障\n■ 就家居財物損毀作出賠償,惟不包括樓宇部分、固定裝置及配置(除非是\n由受保人自行添置的室內裝修,詳情請參考下列註釋)\n■ 家居財物的損毀,應由意外性質事件所導致。因此,若因1. 自然損耗2.蛀\n蟲3. 害蟲4. 昆蟲5. 寵物6. 潮濕7.生鏽8.腐爛9. 腐蝕10. 發霉11. 濕氣12.陽\n光或大氣作用及13.以漸進原因所導致或促成的損毀,是不獲保障的\n■ 當意外性質事件發生時,應立即阻止,減低損失\n■ 因電力或機械故障、錯亂、負荷過多或不足所導致的電器損毀是不獲保障\n的\n■ 玻璃物件(包括鏡、陶瓷器、陶器、土器及水晶擺設)因火災、爆炸、爆\n竊或盜竊而被打碎是獲保障的\n■ 若室內裝修、固定裝置及配置由受保人自行添置,皆可被視作家居財物。\n請提供自行添置這些室內裝修、固定裝置及配置的證明,例如原有安裝收\n據正本等。否則,這些物件將被視作樓宇一部分,並只會在保單中另有投\n保樓宇結構保障項目的情況下受保\n不保障手提電話損毀,除非受保人已支付額外保費,特別為該手提電話投\n保\n■\n任何於清潔、修改、維修、翻新、保養或漂染過程中,或錯誤使用、違反\n製造商指引下使用、內在缺陷、物料、圖樣或規格上的設計錯誤、或逐漸\n變壞及變型等所導致的損毀是不受保障的\n12.2.2 滲水至第三者單單位情況\n■ 在滲水出現時,就受保人可能需要負上的法律責任,即因疏忽而導致第三\n者損失,作出處理及賠償\n■ 當發現滲水,不論第三者有否追討賠償,受保人都應立即填寫索償表格並\n交予我們作通知,在得悉有關情況後,我們將為賠償事宜作出考慮與安排\n■ 受保人應立即找出滲水的源頭,及在有需要時安排維修人員維修\n■ 如收到索償信、律師信或法庭傳票等,請勿私自回覆,並應立即交予我們\n■ 請勿私自向任何第三者承認責任或作出賠償承諾\n■ 如第三者向受保人追討賠償,請要求第三者以書面形式列明其要求。當受\n保人收到第三者的書面索償,請立即交予我們。如有需要,我們將直接聯\n絡第三者\nConfidential 37\n此為機密文件,及只作內部業務用途。請勿轉發。\n請注意:整個銷售過程及所有申請程序必須在香港進行",
          "filename": "Home landlord_Sales Toolkit 26 April 2022.pdf",
          "page_number": null,
          "score": 0.02124183066189289,
          "content_chunk": "保誠精選「業主寶」2022\n12. 索償\n12.1 客戶可經 eClaims申請索償。\n$\n· 只需經手機或電腦登記及登入myPrudential,在\n發生事故後的31天內,上載數份所需索償表格\n及文件,就能申請電子索償,不但隨時隨地查閱\n索償狀態,日後更可輕鬆查閱保單詳情。\nConfidential\n36\n此為機密文件,及只作內部業務用途。請勿轉發。\n請注意:整個銷售過程及所有申請程序必須在香港進行保誠精選「業主寶」2022\n12. 索償\n12.2 索償項目\n12.2.1 家居財物/個人財物失竊保障\n■ 就家居財物損毀作出賠償,惟不包括樓宇部分、固定裝置及配置(除非是\n由受保人自行添置的室內裝修,詳情請參考下列註釋)\n■ 家居財物的損毀,應由意外性質事件所導致。因此,若因1. 自然損耗2.蛀\n蟲3. 害蟲4. 昆蟲5. 寵物6. 潮濕7.生鏽8.腐爛9. 腐蝕10. 發霉11. 濕氣12.陽\n光或大氣作用及13.以漸進原因所導致或促成的損毀,是不獲保障的\n■ 當意外性質事件發生時,應立即阻止,減低損失\n■ 因電力或機械故障、錯亂、負荷過多或不足所導致的電器損毀是不獲保障\n的\n■ 玻璃物件(包括鏡、陶瓷器、陶器、土器及水晶擺設)因火災、爆炸、爆\n竊或盜竊而被打碎是獲保障的\n■ 若室內裝修、固定裝置及配置由受保人自行添置,皆可被視作家居財物。\n請提供自行添置這些室內裝修、固定裝置及配置的證明,例如原有安裝收\n據正本等。否則,這些物件將被視作樓宇一部分,並只會在保單中另有投\n保樓宇結構保障項目的情況下受保\n不保障手提電話損毀,除非受保人已支付額外保費,特別為該手提電話投\n保\n■\n任何於清潔、修改、維修、翻新、保養或漂染過程中,或錯誤使用、違反\n製造商指引下使用、內在缺陷、物料、圖樣或規格上的設計錯誤、或逐漸\n變壞及變型等所導致的損毀是不受保障的\n12.2.2 滲水至第三者單單位情況\n■ 在滲水出現時,就受保人可能需要負上的法律責任,即因疏忽而導致第三\n者損失,作出處理及賠償\n■ 當發現滲水,不論第三者有否追討賠償,受保人都應立即填寫索償表格並\n交予我們作通知,在得悉有關情況後,我們將為賠償事宜作出考慮與安排\n■ 受保人應立即找出滲水的源頭,及在有需要時安排維修人員維修\n■ 如收到索償信、律師信或法庭傳票等,請勿私自回覆,並應立即交予我們\n■ 請勿私自向任何第三者承認責任或作出賠償承諾\n■ 如第三者向受保人追討賠償,請要求第三者以書面形式列明其要求。當受\n保人收到第三者的書面索償,請立即交予我們。如有需要,我們將直接聯\n絡第三者\nConfidential 37\n此為機密文件,及只作內部業務用途。請勿轉發。\n請注意:整個銷售過程及所有申請程序必須在香港進行"
        },
        {
          "id": "GI000028",
          "document_id": "GI000028",
          "title_name_en": "GIEB Training Courses Material",
          "title_name_tc": "GIEB 培訓課程資料",
          "content_en": "●103\n索償個案分享\n一次\n答案\n受保人的索償內容如下:\n1. 第三者索償\n索償金額\n賠償金額\n窗\n5,000\n5,000\nConfidential\n103●104\n索償個案分享\n答案-2. 家居財物\n財物\n索償金額\n賠償金額\n音響設備(包括兩對喇叭)\n80,000\n75,000\n衣櫃\n5,000\n5,000\n衣物\n10,000\n8,000\n手錶\n20,000\n10,000\n牆紙\nNE\n10,000\n9,000\n受保人安裝的地板\n20,000\n20,000\n臨時居所租金\n5,000\n5,000\n總賠償金額\n132,000\n扣:自負額\n250\n淨賠償金額\n131,750\nConfidential\n104",
          "content_tc": "●103\n索償個案分享\n一次\n答案\n受保人的索償內容如下:\n1. 第三者索償\n索償金額\n賠償金額\n窗\n5,000\n5,000\nConfidential\n103●104\n索償個案分享\n答案-2. 家居財物\n財物\n索償金額\n賠償金額\n音響設備(包括兩對喇叭)\n80,000\n75,000\n衣櫃\n5,000\n5,000\n衣物\n10,000\n8,000\n手錶\n20,000\n10,000\n牆紙\nNE\n10,000\n9,000\n受保人安裝的地板\n20,000\n20,000\n臨時居所租金\n5,000\n5,000\n總賠償金額\n132,000\n扣:自負額\n250\n淨賠償金額\n131,750\nConfidential\n104",
          "filename": "Training for Home_Maid_202309_clean_PIL.pdf",
          "page_number": null,
          "score": 0.020000001415610313,
          "content_chunk": "●103\n索償個案分享\n一次\n答案\n受保人的索償內容如下:\n1. 第三者索償\n索償金額\n賠償金額\n窗\n5,000\n5,000\nConfidential\n103●104\n索償個案分享\n答案-2. 家居財物\n財物\n索償金額\n賠償金額\n音響設備(包括兩對喇叭)\n80,000\n75,000\n衣櫃\n5,000\n5,000\n衣物\n10,000\n8,000\n手錶\n20,000\n10,000\n牆紙\nNE\n10,000\n9,000\n受保人安裝的地板\n20,000\n20,000\n臨時居所租金\n5,000\n5,000\n總賠償金額\n132,000\n扣:自負額\n250\n淨賠償金額\n131,750\nConfidential\n104"
        },
        {
          "id": "GI000028",
          "document_id": "GI000028",
          "title_name_en": "GIEB Training Courses Material",
          "title_name_tc": "GIEB 培訓課程資料",
          "content_en": "●101\n索償個案分享\n一次\n問題1.\n實際賠償金額是多少?\n受保人的索償內容如下:\n1. 第三者索償\n索償金額\n賠償金額\n窗\n5,000\n??\nConfidential\n101●102\n索償個案分享\nージ\n2. 家居財物\n財物\n索償金額\n賠償金額\n音響設備(包括兩對喇叭)\n80,000\n??\n衣櫃\n5,000\n??\n衣物\n10,000\n??\n手錶\n20,000\n??\n牆紙\n10,000\n??\n受保人安裝的地板\n20,000\n??\n臨時居所租金\n5,000\n??\n總賠償金額\n??\n扣:自負額\n??\n淨賠償金額\n??\nConfidential\n102",
          "content_tc": "●101\n索償個案分享\n一次\n問題1.\n實際賠償金額是多少?\n受保人的索償內容如下:\n1. 第三者索償\n索償金額\n賠償金額\n窗\n5,000\n??\nConfidential\n101●102\n索償個案分享\nージ\n2. 家居財物\n財物\n索償金額\n賠償金額\n音響設備(包括兩對喇叭)\n80,000\n??\n衣櫃\n5,000\n??\n衣物\n10,000\n??\n手錶\n20,000\n??\n牆紙\n10,000\n??\n受保人安裝的地板\n20,000\n??\n臨時居所租金\n5,000\n??\n總賠償金額\n??\n扣:自負額\n??\n淨賠償金額\n??\nConfidential\n102",
          "filename": "Training for Home_Maid_202309_clean_PIL.pdf",
          "page_number": null,
          "score": 0.01973792351782322,
          "content_chunk": "●101\n索償個案分享\n一次\n問題1.\n實際賠償金額是多少?\n受保人的索償內容如下:\n1. 第三者索償\n索償金額\n賠償金額\n窗\n5,000\n??\nConfidential\n101●102\n索償個案分享\nージ\n2. 家居財物\n財物\n索償金額\n賠償金額\n音響設備(包括兩對喇叭)\n80,000\n??\n衣櫃\n5,000\n??\n衣物\n10,000\n??\n手錶\n20,000\n??\n牆紙\n10,000\n??\n受保人安裝的地板\n20,000\n??\n臨時居所租金\n5,000\n??\n總賠償金額\n??\n扣:自負額\n??\n淨賠償金額\n??\nConfidential\n102"
        },
        {
          "id": "GI000161",
          "document_id": "GI000161",
          "title_name_en": "PRUChoice Relocation Care",
          "title_name_tc": "保誠精選「移居寶」",
          "content_en": " than 8 years old\n· Medical conditions caused by special conditions such as plague\n· Congenital diseases\n· Conditions caused by negligent care or deliberate act\n· Denture and related treatment\n· Preventive and selective treatment\nPremium Table\nBasic Plan (HK$)\nPremier Plan (HK$)\nInsured Person Only\n1,300\n2,300\nInsured Person & Family#\n3,600\n6,300\n# \"Insured Person & Family\" refers to the Insured Person, his/ her legally married spouse, dependent\nand unmarried children who are age of 17 or below.保誠精選「移居寶」保障計劃\n與您的摯愛移居到陌生的目的地重新出發並不容易。不論您移居到\n何處,您都擁有保誠最堅實及全面的支持。保誠財險有限公司\n(「保誠」)明白您的需要,並誠意為您獻上保誠精選「移居寶」\n保障計劃,讓您於出發日起計的首90天盡快適應新環境,無憂無慮\n開展您美好的第二人生。\n(2022年3月15日或之後適用)\n計劃特點\n1\n保誠精選「移居寶」各項保障,均不設「自負金額」。\n2\n保障涵蓋醫療、意外及家庭部份,令您安心適應新生活。\n3\n保障設有單人或家庭計劃以供選擇。\n4\n「寵物保障」確保您的愛狗或愛貓能樂享新生活。\n5\n尊尚計劃的醫療費用及人身意外保障最高保障額可達港幣\n$1,200,000 °\n6\n特設心理援助保障,照顧您在移居目的地因親歷意外或天災所\n引致的心理創傷。\n7\n若您未能如期起程,而於90天內重新出發,將獲享「免費延\n長90天保障」\n8\n傭工支援及摯親支援為您提供強大保障,讓您專心與家人享受\n快樂時光。\n保障一覽表\n(所有項目不設「自負金額」)\n主要保障\n每名受保人最高保障額\n(港幣$)\n基本計劃\n尊尚計劃\n1. 醫療保障\n600,000\n1,200,000\n海外住院\n每天2,000,\n每天4,000,\n前往移居目的地途中或在移居目的地意\n最高\n最高\n外受傷或患病,賠償必須且合理的醫療\n100,000\n200,000\n開支,包括住院及膳食、住院雜項、深\n切治療、住院治療之醫生及專科醫生費\n用、醫療器材、住院陪床及前往當地醫\n院的緊急交通費用。\n海外手術\n每次手術\n每次手術\n若您於前往移居目的地途中或在移居目\n的地意外受傷或患病而不幸需要做手\n術,我們將賠償有關的手術費用,包括\n外科醫生費,麻醉科醫生費及手術室租\n金。\n150,000\n250,000\n海外門診\n每天最多\n每天最多\n一次4,000,\n若您於前往移居目的地途中或在移居目\n一次2,000,\n最高30,000\n最高60,000\n的地意外受傷或患病而需看醫生,我們\n將賠償有關的醫療開支,包括門診、於\n就醫翌日購買有關處方藥物、門診X光及\n化驗測試。\n心理援助\n每天最多\n每天最多\n因您在移居目的地因意外嚴重受傷、親\n一次2,000,\n一次4,000,\n歷恐怖主義襲擊或天災(包括但不限於\n地震、海嘯、龍捲風及火山爆發)所引\n致的心理創傷,並於住院後仍需經普通\n科醫生轉介下尋求精神科醫生的治療,\n我們將賠償有關的精神科醫生費用。\n最高40,000\n最高80,000\n2. 意外保障\n700,000\n1,400,000\n人身意外\n600,000\n1,200,000\n您於前往移居目的地途中或在移居目的\n地因意外直接引致的意外死亡、完全永\n久傷殘、完全永久性斷肢、失明、喪失\n語言能力及聽覺,可獲100%保障額。延\n伸保障其他永久性傷殘,我們將根據保\n障賠償表所列之最高賠償額作出賠償。\n殮葬費用\n50,000\n100,000\n支付因意外身亡引起的海外殮葬費用。\n親友善後\n50,000\n100,000\n如您在外地意外身亡,支付一位親屬或\n朋友需要前往當地善後的住宿及交通費\n用。\n3. 車輛自負額\n3,000\n6,000\n若受保人在移居目的地駕駛所擁有的車\n輛,意外發生碰撞,或該車輛被偷竊或\n在停泊時損毀,當您所安排的汽車保單\n就此作出賠償時,我們亦會賠償您須負\n責的有關自負額。\n4. 旅程受阻\n40,000\n80,000\n行程受阻\n10,000\n20,000\n若您於出發前的7日內因出現下列不能控\n制的原因而無可避免地令您的旅程受阻,\n我們將賠償您已繳付或立約支付而未能退\n回的機票費用:\n1. 受保人或其同行直系親屬*身故、嚴重\n身體損傷或患病,並由醫生證明不適\n宜移居;\n2.\n受保人的直系親屬*身故、嚴重身體損\n傷或患嚴重疾病,並由醫生證明。\n意外住院保障\n30,000\n60,000\n若您於出發前的7日內因意外受傷而需於\n香港住院超過連續24小時,我們將賠償有\n關的住院醫療開支。\n免費延長90天保障\n如因以上項目4內行程受阻或意外住院保\n障引致您的旅程受阻,受保人需於原出發\n日之前以書面提出有效的索償後延遲保單\n生效日。當您於原出發日起計90天內重新\n出發,所有保障將由您重新出發日起計免\n費延長90天。每個保單只允許延遲保險期\n一次。\n5. 傭工支援\n每天400,\n每天800,\n最高8,000\n如受保人於移居目的地因發生以下事故,\n我們將賠償僱用傭工的費用,\n最高4,000\n● 死亡或患上末期疾病+;或\n● 連續住院達5日或以上。\n6. 摯親支援\n4,000\n8,000\n如受保人的直系親屬*於香港身故、嚴重\n身體損傷或患病,我們將賠償您需要返回\n香港的交通費用。\n7. 傢俱未能送抵\n保障專業搬運/ 運輸公司由香港運送傢俱\n至您移居目的地的新住所,傢俱包括床\n墊、床具、沙發、櫃子、書櫃和衣櫃,因\n遺失而未能送抵,並由專業搬運/運輸公\n司確認未能由預定收貨日起計60天內退\n款予您。\n每件5,000,\n最高20,000 最高40,000\n每件5,000,",
          "content_tc": " than 8 years old\n· Medical conditions caused by special conditions such as plague\n· Congenital diseases\n· Conditions caused by negligent care or deliberate act\n· Denture and related treatment\n· Preventive and selective treatment\nPremium Table\nBasic Plan (HK$)\nPremier Plan (HK$)\nInsured Person Only\n1,300\n2,300\nInsured Person & Family#\n3,600\n6,300\n# \"Insured Person & Family\" refers to the Insured Person, his/ her legally married spouse, dependent\nand unmarried children who are age of 17 or below.保誠精選「移居寶」保障計劃\n與您的摯愛移居到陌生的目的地重新出發並不容易。不論您移居到\n何處,您都擁有保誠最堅實及全面的支持。保誠財險有限公司\n(「保誠」)明白您的需要,並誠意為您獻上保誠精選「移居寶」\n保障計劃,讓您於出發日起計的首90天盡快適應新環境,無憂無慮\n開展您美好的第二人生。\n(2022年3月15日或之後適用)\n計劃特點\n1\n保誠精選「移居寶」各項保障,均不設「自負金額」。\n2\n保障涵蓋醫療、意外及家庭部份,令您安心適應新生活。\n3\n保障設有單人或家庭計劃以供選擇。\n4\n「寵物保障」確保您的愛狗或愛貓能樂享新生活。\n5\n尊尚計劃的醫療費用及人身意外保障最高保障額可達港幣\n$1,200,000 °\n6\n特設心理援助保障,照顧您在移居目的地因親歷意外或天災所\n引致的心理創傷。\n7\n若您未能如期起程,而於90天內重新出發,將獲享「免費延\n長90天保障」\n8\n傭工支援及摯親支援為您提供強大保障,讓您專心與家人享受\n快樂時光。\n保障一覽表\n(所有項目不設「自負金額」)\n主要保障\n每名受保人最高保障額\n(港幣$)\n基本計劃\n尊尚計劃\n1. 醫療保障\n600,000\n1,200,000\n海外住院\n每天2,000,\n每天4,000,\n前往移居目的地途中或在移居目的地意\n最高\n最高\n外受傷或患病,賠償必須且合理的醫療\n100,000\n200,000\n開支,包括住院及膳食、住院雜項、深\n切治療、住院治療之醫生及專科醫生費\n用、醫療器材、住院陪床及前往當地醫\n院的緊急交通費用。\n海外手術\n每次手術\n每次手術\n若您於前往移居目的地途中或在移居目\n的地意外受傷或患病而不幸需要做手\n術,我們將賠償有關的手術費用,包括\n外科醫生費,麻醉科醫生費及手術室租\n金。\n150,000\n250,000\n海外門診\n每天最多\n每天最多\n一次4,000,\n若您於前往移居目的地途中或在移居目\n一次2,000,\n最高30,000\n最高60,000\n的地意外受傷或患病而需看醫生,我們\n將賠償有關的醫療開支,包括門診、於\n就醫翌日購買有關處方藥物、門診X光及\n化驗測試。\n心理援助\n每天最多\n每天最多\n因您在移居目的地因意外嚴重受傷、親\n一次2,000,\n一次4,000,\n歷恐怖主義襲擊或天災(包括但不限於\n地震、海嘯、龍捲風及火山爆發)所引\n致的心理創傷,並於住院後仍需經普通\n科醫生轉介下尋求精神科醫生的治療,\n我們將賠償有關的精神科醫生費用。\n最高40,000\n最高80,000\n2. 意外保障\n700,000\n1,400,000\n人身意外\n600,000\n1,200,000\n您於前往移居目的地途中或在移居目的\n地因意外直接引致的意外死亡、完全永\n久傷殘、完全永久性斷肢、失明、喪失\n語言能力及聽覺,可獲100%保障額。延\n伸保障其他永久性傷殘,我們將根據保\n障賠償表所列之最高賠償額作出賠償。\n殮葬費用\n50,000\n100,000\n支付因意外身亡引起的海外殮葬費用。\n親友善後\n50,000\n100,000\n如您在外地意外身亡,支付一位親屬或\n朋友需要前往當地善後的住宿及交通費\n用。\n3. 車輛自負額\n3,000\n6,000\n若受保人在移居目的地駕駛所擁有的車\n輛,意外發生碰撞,或該車輛被偷竊或\n在停泊時損毀,當您所安排的汽車保單\n就此作出賠償時,我們亦會賠償您須負\n責的有關自負額。\n4. 旅程受阻\n40,000\n80,000\n行程受阻\n10,000\n20,000\n若您於出發前的7日內因出現下列不能控\n制的原因而無可避免地令您的旅程受阻,\n我們將賠償您已繳付或立約支付而未能退\n回的機票費用:\n1. 受保人或其同行直系親屬*身故、嚴重\n身體損傷或患病,並由醫生證明不適\n宜移居;\n2.\n受保人的直系親屬*身故、嚴重身體損\n傷或患嚴重疾病,並由醫生證明。\n意外住院保障\n30,000\n60,000\n若您於出發前的7日內因意外受傷而需於\n香港住院超過連續24小時,我們將賠償有\n關的住院醫療開支。\n免費延長90天保障\n如因以上項目4內行程受阻或意外住院保\n障引致您的旅程受阻,受保人需於原出發\n日之前以書面提出有效的索償後延遲保單\n生效日。當您於原出發日起計90天內重新\n出發,所有保障將由您重新出發日起計免\n費延長90天。每個保單只允許延遲保險期\n一次。\n5. 傭工支援\n每天400,\n每天800,\n最高8,000\n如受保人於移居目的地因發生以下事故,\n我們將賠償僱用傭工的費用,\n最高4,000\n● 死亡或患上末期疾病+;或\n● 連續住院達5日或以上。\n6. 摯親支援\n4,000\n8,000\n如受保人的直系親屬*於香港身故、嚴重\n身體損傷或患病,我們將賠償您需要返回\n香港的交通費用。\n7. 傢俱未能送抵\n保障專業搬運/ 運輸公司由香港運送傢俱\n至您移居目的地的新住所,傢俱包括床\n墊、床具、沙發、櫃子、書櫃和衣櫃,因\n遺失而未能送抵,並由專業搬運/運輸公\n司確認未能由預定收貨日起計60天內退\n款予您。\n每件5,000,\n最高20,000 最高40,000\n每件5,000,",
          "filename": "PRUChoice Relocation care brochure 0524.pdf",
          "page_number": null,
          "score": 0.019414985552430153,
          "content_chunk": " than 8 years old\n· Medical conditions caused by special conditions such as plague\n· Congenital diseases\n· Conditions caused by negligent care or deliberate act\n· Denture and related treatment\n· Preventive and selective treatment\nPremium Table\nBasic Plan (HK$)\nPremier Plan (HK$)\nInsured Person Only\n1,300\n2,300\nInsured Person & Family#\n3,600\n6,300\n# \"Insured Person & Family\" refers to the Insured Person, his/ her legally married spouse, dependent\nand unmarried children who are age of 17 or below.保誠精選「移居寶」保障計劃\n與您的摯愛移居到陌生的目的地重新出發並不容易。不論您移居到\n何處,您都擁有保誠最堅實及全面的支持。保誠財險有限公司\n(「保誠」)明白您的需要,並誠意為您獻上保誠精選「移居寶」\n保障計劃,讓您於出發日起計的首90天盡快適應新環境,無憂無慮\n開展您美好的第二人生。\n(2022年3月15日或之後適用)\n計劃特點\n1\n保誠精選「移居寶」各項保障,均不設「自負金額」。\n2\n保障涵蓋醫療、意外及家庭部份,令您安心適應新生活。\n3\n保障設有單人或家庭計劃以供選擇。\n4\n「寵物保障」確保您的愛狗或愛貓能樂享新生活。\n5\n尊尚計劃的醫療費用及人身意外保障最高保障額可達港幣\n$1,200,000 °\n6\n特設心理援助保障,照顧您在移居目的地因親歷意外或天災所\n引致的心理創傷。\n7\n若您未能如期起程,而於90天內重新出發,將獲享「免費延\n長90天保障」\n8\n傭工支援及摯親支援為您提供強大保障,讓您專心與家人享受\n快樂時光。\n保障一覽表\n(所有項目不設「自負金額」)\n主要保障\n每名受保人最高保障額\n(港幣$)\n基本計劃\n尊尚計劃\n1. 醫療保障\n600,000\n1,200,000\n海外住院\n每天2,000,\n每天4,000,\n前往移居目的地途中或在移居目的地意\n最高\n最高\n外受傷或患病,賠償必須且合理的醫療\n100,000\n200,000\n開支,包括住院及膳食、住院雜項、深\n切治療、住院治療之醫生及專科醫生費\n用、醫療器材、住院陪床及前往當地醫\n院的緊急交通費用。\n海外手術\n每次手術\n每次手術\n若您於前往移居目的地途中或在移居目\n的地意外受傷或患病而不幸需要做手\n術,我們將賠償有關的手術費用,包括\n外科醫生費,麻醉科醫生費及手術室租\n金。\n150,000\n250,000\n海外門診\n每天最多\n每天最多\n一次4,000,\n若您於前往移居目的地途中或在移居目\n一次2,000,\n最高30,000\n最高60,000\n的地意外受傷或患病而需看醫生,我們\n將賠償有關的醫療開支,包括門診、於\n就醫翌日購買有關處方藥物、門診X光及\n化驗測試。\n心理援助\n每天最多\n每天最多\n因您在移居目的地因意外嚴重受傷、親\n一次2,000,\n一次4,000,\n歷恐怖主義襲擊或天災(包括但不限於\n地震、海嘯、龍捲風及火山爆發)所引\n致的心理創傷,並於住院後仍需經普通\n科醫生轉介下尋求精神科醫生的治療,\n我們將賠償有關的精神科醫生費用。\n最高40,000\n最高80,000\n2. 意外保障\n700,000\n1,400,000\n人身意外\n600,000\n1,200,000\n您於前往移居目的地途中或在移居目的\n地因意外直接引致的意外死亡、完全永\n久傷殘、完全永久性斷肢、失明、喪失\n語言能力及聽覺,可獲100%保障額。延\n伸保障其他永久性傷殘,我們將根據保\n障賠償表所列之最高賠償額作出賠償。\n殮葬費用\n50,000\n100,000\n支付因意外身亡引起的海外殮葬費用。\n親友善後\n50,000\n100,000\n如您在外地意外身亡,支付一位親屬或\n朋友需要前往當地善後的住宿及交通費\n用。\n3. 車輛自負額\n3,000\n6,000\n若受保人在移居目的地駕駛所擁有的車\n輛,意外發生碰撞,或該車輛被偷竊或\n在停泊時損毀,當您所安排的汽車保單\n就此作出賠償時,我們亦會賠償您須負\n責的有關自負額。\n4. 旅程受阻\n40,000\n80,000\n行程受阻\n10,000\n20,000\n若您於出發前的7日內因出現下列不能控\n制的原因而無可避免地令您的旅程受阻,\n我們將賠償您已繳付或立約支付而未能退\n回的機票費用:\n1. 受保人或其同行直系親屬*身故、嚴重\n身體損傷或患病,並由醫生證明不適\n宜移居;\n2.\n受保人的直系親屬*身故、嚴重身體損\n傷或患嚴重疾病,並由醫生證明。\n意外住院保障\n30,000\n60,000\n若您於出發前的7日內因意外受傷而需於\n香港住院超過連續24小時,我們將賠償有\n關的住院醫療開支。\n免費延長90天保障\n如因以上項目4內行程受阻或意外住院保\n障引致您的旅程受阻,受保人需於原出發\n日之前以書面提出有效的索償後延遲保單\n生效日。當您於原出發日起計90天內重新\n出發,所有保障將由您重新出發日起計免\n費延長90天。每個保單只允許延遲保險期\n一次。\n5. 傭工支援\n每天400,\n每天800,\n最高8,000\n如受保人於移居目的地因發生以下事故,\n我們將賠償僱用傭工的費用,\n最高4,000\n● 死亡或患上末期疾病+;或\n● 連續住院達5日或以上。\n6. 摯親支援\n4,000\n8,000\n如受保人的直系親屬*於香港身故、嚴重\n身體損傷或患病,我們將賠償您需要返回\n香港的交通費用。\n7. 傢俱未能送抵\n保障專業搬運/ 運輸公司由香港運送傢俱\n至您移居目的地的新住所,傢俱包括床\n墊、床具、沙發、櫃子、書櫃和衣櫃,因\n遺失而未能送抵,並由專業搬運/運輸公\n司確認未能由預定收貨日起計60天內退\n款予您。\n每件5,000,\n最高20,000 最高40,000\n每件5,000,"
        },
        {
          "id": "GI000028",
          "document_id": "GI000028",
          "title_name_en": "GIEB Training Courses Material",
          "title_name_tc": "GIEB 培訓課程資料",
          "content_en": "●104\n索償個案分享\n答案-2. 家居財物\n財物\n索償金額\n賠償金額\n音響設備(包括兩對喇叭)\n80,000\n75,000\n衣櫃\n5,000\n5,000\n衣物\n10,000\n8,000\n手錶\n20,000\n10,000\n牆紙\nNE\n10,000\n9,000\n受保人安裝的地板\n20,000\n20,000\n臨時居所租金\n5,000\n5,000\n總賠償金額\n132,000\n扣:自負額\n250\n淨賠償金額\n131,750\nConfidential\n104●105\n索償個案分享\n答案\n一次\n財物\n賠償金額\n原因\n音響設備(包括兩對喇叭)\n75,000\n每件最高限額\n衣櫃\n5,000\n衣物\n8,000\n扣除折舊\n手錶\n10,000\n每件最高限額\n牆紙\n9,000\n扣除自負金額\nHK$1,000\n受保人安裝的地板\n20,000\n臨時居所租金\n5,000\nConfidential\n105",
          "content_tc": "●104\n索償個案分享\n答案-2. 家居財物\n財物\n索償金額\n賠償金額\n音響設備(包括兩對喇叭)\n80,000\n75,000\n衣櫃\n5,000\n5,000\n衣物\n10,000\n8,000\n手錶\n20,000\n10,000\n牆紙\nNE\n10,000\n9,000\n受保人安裝的地板\n20,000\n20,000\n臨時居所租金\n5,000\n5,000\n總賠償金額\n132,000\n扣:自負額\n250\n淨賠償金額\n131,750\nConfidential\n104●105\n索償個案分享\n答案\n一次\n財物\n賠償金額\n原因\n音響設備(包括兩對喇叭)\n75,000\n每件最高限額\n衣櫃\n5,000\n衣物\n8,000\n扣除折舊\n手錶\n10,000\n每件最高限額\n牆紙\n9,000\n扣除自負金額\nHK$1,000\n受保人安裝的地板\n20,000\n臨時居所租金\n5,000\nConfidential\n105",
          "filename": "Training for Home_Maid_202309_clean_PIL.pdf",
          "page_number": null,
          "score": 0.019187135621905327,
          "content_chunk": "●104\n索償個案分享\n答案-2. 家居財物\n財物\n索償金額\n賠償金額\n音響設備(包括兩對喇叭)\n80,000\n75,000\n衣櫃\n5,000\n5,000\n衣物\n10,000\n8,000\n手錶\n20,000\n10,000\n牆紙\nNE\n10,000\n9,000\n受保人安裝的地板\n20,000\n20,000\n臨時居所租金\n5,000\n5,000\n總賠償金額\n132,000\n扣:自負額\n250\n淨賠償金額\n131,750\nConfidential\n104●105\n索償個案分享\n答案\n一次\n財物\n賠償金額\n原因\n音響設備(包括兩對喇叭)\n75,000\n每件最高限額\n衣櫃\n5,000\n衣物\n8,000\n扣除折舊\n手錶\n10,000\n每件最高限額\n牆紙\n9,000\n扣除自負金額\nHK$1,000\n受保人安裝的地板\n20,000\n臨時居所租金\n5,000\nConfidential\n105"
        },
        {
          "id": "GI000029",
          "document_id": "GI000029",
          "title_name_en": "Bulletins",
          "title_name_tc": "通訊",
          "content_en": "GI通訊\n家居財物 保誠精選「家居寶」保障您安樂窩的損失\nGI 市場推廣部\n2023年5月\nyahoo!新聞 | 17.5k 人追蹤\n☆ 追蹤\n水濕損毀\n超崩潰!天寰水錶房爆喉 業主要賠100\n萬?\n爆食水喉\n天寰\nMicrOFTHE\nSkve\nR.W.P\n管理處事後告知,引發水浸事件是水錶房一條食水喉爆裂,\n而該水喉僅供水予Crystal的單位使用,要求她自行找水喉匠\n維修,她當時大感錯愕\nCrystal直言無買家居保險,十分擔心,據知大廈曾維修兩次\n升降機,分別為爆鹹水管及黑雨,每次維修費均高達100萬\n元,倘今次要面對過百萬元賠償,大感無辜之餘,還直言無\n力支付,「呢個數相當於一筆首期,咁樣我真係要賣樓\n喇!」\n漏水浸壞了同層其中一部升降機,或會追討她賠償維修\n費,着她找保險公司商討,「我好震驚!平時水錶房係上\n鎖,我入唔到去,壞咗就要我負責?」\n資料來源:YAHOO!新聞\n此為機密文件,及只作內部業務用途。請勿轉發。\nConfidential\n6GI通訊\n家居財物 保誠精選「家居寶」保障您安樂窩的損失\nGI 市場推廣部\n2023年5月\nPRUeShop 網上投保!\n安在家中獲享\n即時的家居保障\n保誠精選「家居寶」不但保障全面,更是市場上極具競爭力的產\n品。多個市場獨有特點,全面照顧客人重視家中的一切。\n•\n全球個人財物保障,每年高達港幣$40,000\nwww\n•\n全面保障您在互聯網上可能遇上的風險包括欺詐網站、網上\n購物及個人身份被盜用等\n•\n自選「家庭電器保養服務保障」,保障您的家庭電器因機械\n及電器故障而引致之維修費用\nD\n•\n家居意外保障,若因家居火災、持械行劫或盜竊,導致您及\n您家人身亡、完全永久傷殘、喪失肢體或喪失視力,將獲得\n賠償\n此為機密文件,及只作內部業務用途。請勿轉發。\nConfidential\n7",
          "content_tc": "GI通訊\n家居財物 保誠精選「家居寶」保障您安樂窩的損失\nGI 市場推廣部\n2023年5月\nyahoo!新聞 | 17.5k 人追蹤\n☆ 追蹤\n水濕損毀\n超崩潰!天寰水錶房爆喉 業主要賠100\n萬?\n爆食水喉\n天寰\nMicrOFTHE\nSkve\nR.W.P\n管理處事後告知,引發水浸事件是水錶房一條食水喉爆裂,\n而該水喉僅供水予Crystal的單位使用,要求她自行找水喉匠\n維修,她當時大感錯愕\nCrystal直言無買家居保險,十分擔心,據知大廈曾維修兩次\n升降機,分別為爆鹹水管及黑雨,每次維修費均高達100萬\n元,倘今次要面對過百萬元賠償,大感無辜之餘,還直言無\n力支付,「呢個數相當於一筆首期,咁樣我真係要賣樓\n喇!」\n漏水浸壞了同層其中一部升降機,或會追討她賠償維修\n費,着她找保險公司商討,「我好震驚!平時水錶房係上\n鎖,我入唔到去,壞咗就要我負責?」\n資料來源:YAHOO!新聞\n此為機密文件,及只作內部業務用途。請勿轉發。\nConfidential\n6GI通訊\n家居財物 保誠精選「家居寶」保障您安樂窩的損失\nGI 市場推廣部\n2023年5月\nPRUeShop 網上投保!\n安在家中獲享\n即時的家居保障\n保誠精選「家居寶」不但保障全面,更是市場上極具競爭力的產\n品。多個市場獨有特點,全面照顧客人重視家中的一切。\n•\n全球個人財物保障,每年高達港幣$40,000\nwww\n•\n全面保障您在互聯網上可能遇上的風險包括欺詐網站、網上\n購物及個人身份被盜用等\n•\n自選「家庭電器保養服務保障」,保障您的家庭電器因機械\n及電器故障而引致之維修費用\nD\n•\n家居意外保障,若因家居火災、持械行劫或盜竊,導致您及\n您家人身亡、完全永久傷殘、喪失肢體或喪失視力,將獲得\n賠償\n此為機密文件,及只作內部業務用途。請勿轉發。\nConfidential\n7",
          "filename": "【GI通訊】通訊家居財物 保誠精選「家居寶」保障您安樂窩的損失.pdf",
          "page_number": null,
          "score": 0.019145919010043144,
          "content_chunk": "GI通訊\n家居財物 保誠精選「家居寶」保障您安樂窩的損失\nGI 市場推廣部\n2023年5月\nyahoo!新聞 | 17.5k 人追蹤\n☆ 追蹤\n水濕損毀\n超崩潰!天寰水錶房爆喉 業主要賠100\n萬?\n爆食水喉\n天寰\nMicrOFTHE\nSkve\nR.W.P\n管理處事後告知,引發水浸事件是水錶房一條食水喉爆裂,\n而該水喉僅供水予Crystal的單位使用,要求她自行找水喉匠\n維修,她當時大感錯愕\nCrystal直言無買家居保險,十分擔心,據知大廈曾維修兩次\n升降機,分別為爆鹹水管及黑雨,每次維修費均高達100萬\n元,倘今次要面對過百萬元賠償,大感無辜之餘,還直言無\n力支付,「呢個數相當於一筆首期,咁樣我真係要賣樓\n喇!」\n漏水浸壞了同層其中一部升降機,或會追討她賠償維修\n費,着她找保險公司商討,「我好震驚!平時水錶房係上\n鎖,我入唔到去,壞咗就要我負責?」\n資料來源:YAHOO!新聞\n此為機密文件,及只作內部業務用途。請勿轉發。\nConfidential\n6GI通訊\n家居財物 保誠精選「家居寶」保障您安樂窩的損失\nGI 市場推廣部\n2023年5月\nPRUeShop 網上投保!\n安在家中獲享\n即時的家居保障\n保誠精選「家居寶」不但保障全面,更是市場上極具競爭力的產\n品。多個市場獨有特點,全面照顧客人重視家中的一切。\n•\n全球個人財物保障,每年高達港幣$40,000\nwww\n•\n全面保障您在互聯網上可能遇上的風險包括欺詐網站、網上\n購物及個人身份被盜用等\n•\n自選「家庭電器保養服務保障」,保障您的家庭電器因機械\n及電器故障而引致之維修費用\nD\n•\n家居意外保障,若因家居火災、持械行劫或盜竊,導致您及\n您家人身亡、完全永久傷殘、喪失肢體或喪失視力,將獲得\n賠償\n此為機密文件,及只作內部業務用途。請勿轉發。\nConfidential\n7"
        },
        {
          "id": "GI000028",
          "document_id": "GI000028",
          "title_name_en": "GIEB Training Courses Material",
          "title_name_tc": "GIEB 培訓課程資料",
          "content_en": "●102\n索償個案分享\nージ\n2. 家居財物\n財物\n索償金額\n賠償金額\n音響設備(包括兩對喇叭)\n80,000\n??\n衣櫃\n5,000\n??\n衣物\n10,000\n??\n手錶\n20,000\n??\n牆紙\n10,000\n??\n受保人安裝的地板\n20,000\n??\n臨時居所租金\n5,000\n??\n總賠償金額\n??\n扣:自負額\n??\n淨賠償金額\n??\nConfidential\n102●103\n索償個案分享\n一次\n答案\n受保人的索償內容如下:\n1. 第三者索償\n索償金額\n賠償金額\n窗\n5,000\n5,000\nConfidential\n103",
          "content_tc": "●102\n索償個案分享\nージ\n2. 家居財物\n財物\n索償金額\n賠償金額\n音響設備(包括兩對喇叭)\n80,000\n??\n衣櫃\n5,000\n??\n衣物\n10,000\n??\n手錶\n20,000\n??\n牆紙\n10,000\n??\n受保人安裝的地板\n20,000\n??\n臨時居所租金\n5,000\n??\n總賠償金額\n??\n扣:自負額\n??\n淨賠償金額\n??\nConfidential\n102●103\n索償個案分享\n一次\n答案\n受保人的索償內容如下:\n1. 第三者索償\n索償金額\n賠償金額\n窗\n5,000\n5,000\nConfidential\n103",
          "filename": "Training for Home_Maid_202309_clean_PIL.pdf",
          "page_number": null,
          "score": 0.01910926215350628,
          "content_chunk": "●102\n索償個案分享\nージ\n2. 家居財物\n財物\n索償金額\n賠償金額\n音響設備(包括兩對喇叭)\n80,000\n??\n衣櫃\n5,000\n??\n衣物\n10,000\n??\n手錶\n20,000\n??\n牆紙\n10,000\n??\n受保人安裝的地板\n20,000\n??\n臨時居所租金\n5,000\n??\n總賠償金額\n??\n扣:自負額\n??\n淨賠償金額\n??\nConfidential\n102●103\n索償個案分享\n一次\n答案\n受保人的索償內容如下:\n1. 第三者索償\n索償金額\n賠償金額\n窗\n5,000\n5,000\nConfidential\n103"
        },
        {
          "id": "GI000028",
          "document_id": "GI000028",
          "title_name_en": "GIEB Training Courses Material",
          "title_name_tc": "GIEB 培訓課程資料",
          "content_en": "●156\n索償注意事項\n一次\n保誠精選「僱傭寶」\n常見索償\n-門診費用(94%)\n常見不獲賠償項目\n- 發生在免責期內的醫療事故(23%)\n- 身體檢查或疫苗注射(22%)\nConfidential\n156●157\n索償注意事項\n一次\n保誠精選「僱傭寶」- 索償所需文件\n僱員賠償\n- 勞工處的表格2/表格2B副本\n- 病假證明書及醫療費用收據正本\n-倘若適用,呈交評估證明書(表格5,7或9)正本\n門診費用及住院和手術費用及牙醫費用\n-列明註冊醫生診斷的醫療費/住院帳單/收據正本\n簡易門診索償程序\n您只需要於附有外籍家庭傭工姓名、病況及診金的正本醫療收\n據背頁寫上有關保單號碼,並將收據交予閣下的理財顧問或寄\n至保誠財險有限公司(香港鯛魚涌華蘭路25號柏克大廈3樓)\n即可。有關其他索償條件,請參閱保單。\nConfidential\n157",
          "content_tc": "●156\n索償注意事項\n一次\n保誠精選「僱傭寶」\n常見索償\n-門診費用(94%)\n常見不獲賠償項目\n- 發生在免責期內的醫療事故(23%)\n- 身體檢查或疫苗注射(22%)\nConfidential\n156●157\n索償注意事項\n一次\n保誠精選「僱傭寶」- 索償所需文件\n僱員賠償\n- 勞工處的表格2/表格2B副本\n- 病假證明書及醫療費用收據正本\n-倘若適用,呈交評估證明書(表格5,7或9)正本\n門診費用及住院和手術費用及牙醫費用\n-列明註冊醫生診斷的醫療費/住院帳單/收據正本\n簡易門診索償程序\n您只需要於附有外籍家庭傭工姓名、病況及診金的正本醫療收\n據背頁寫上有關保單號碼,並將收據交予閣下的理財顧問或寄\n至保誠財險有限公司(香港鯛魚涌華蘭路25號柏克大廈3樓)\n即可。有關其他索償條件,請參閱保單。\nConfidential\n157",
          "filename": "Training for Home_Maid_202309_clean_PIL.pdf",
          "page_number": null,
          "score": 0.01701004058122635,
          "content_chunk": "●156\n索償注意事項\n一次\n保誠精選「僱傭寶」\n常見索償\n-門診費用(94%)\n常見不獲賠償項目\n- 發生在免責期內的醫療事故(23%)\n- 身體檢查或疫苗注射(22%)\nConfidential\n156●157\n索償注意事項\n一次\n保誠精選「僱傭寶」- 索償所需文件\n僱員賠償\n- 勞工處的表格2/表格2B副本\n- 病假證明書及醫療費用收據正本\n-倘若適用,呈交評估證明書(表格5,7或9)正本\n門診費用及住院和手術費用及牙醫費用\n-列明註冊醫生診斷的醫療費/住院帳單/收據正本\n簡易門診索償程序\n您只需要於附有外籍家庭傭工姓名、病況及診金的正本醫療收\n據背頁寫上有關保單號碼,並將收據交予閣下的理財顧問或寄\n至保誠財險有限公司(香港鯛魚涌華蘭路25號柏克大廈3樓)\n即可。有關其他索償條件,請參閱保單。\nConfidential\n157"
        }
      ]
    },
    {
      "query": "如何就家居寶保提出索償?",
      "search_method": "simple",
      "total_result": 10,
      "results": [
        {
          "id": "GI000061",
          "document_id": "GI000061",
          "title_name_en": "PRUchoice Home",
          "title_name_tc": "保誠精選「家居寶」",
          "content_en": "保誠精選「家居寶」2022\n6. 注意事項\n其他事項\n1.\n「貴重財物」包括白金、黃金、珠寶首飾、錶、皮草、藝術品、古\n玩及攝影器材等。\n2.\n「欺詐網站」意指該網站屬欺詐性質,且已經由香港有關監管機構\n公開宣佈。\n3. 「持牌銀行」意指根據香港法例第155章《銀行業條例》於香港\n註冊的持牌銀行。\n4.\n「個人身份被盜用」意指未經授權而使用及/或非法使用您或您的\n家人的姓名或香港身份證號碼等個人資訊開立您或您的家人未授權\n的信用帳戶及/或銀行帳戶。\n5.\n「每件」意指一件、一對或一套物品。\n6.\n「家人」意指一般情況下與您永久同住的父母、兄弟姊妹、配偶、\n子女及親屬,如要為同住朋友投保,請在本申請表中列明。\n7. 就任何終止或更改本保單,按每保單收取港幣$400的最低保費。\nConfidential\n17\n此為機密文件,及只作內部業務用途。請勿轉發。\n請注意:整個銷售過程及所有申請程序必須在香港進行保誠精選「家居寶」2022\n7. 銷售術語\n· 不同客戶都有不同的需求,因此需要注意用詞和話術,特別\n是遇到異議時如何使用說話技巧應對\n點解要買家居保險呢?\n因為可以保障家居財物及室內裝修因意外時損毀所引致的維\n修費用;又或您及您的家人,因疏忽而導致第三者身體受傷\n或財物損失,而需負上的法律責任,都同樣獲得保障。\n客戶表示都住左咁耐,唔使買家居寶保險啦!\n唔好咁諗呀!最重要就係第三者法律責任保障,因為賠償金\n額可大可小,好難估計,所以一定要買保誠精選「家居寶」\n!如果你係業主,仲會有免費額外「業主法律責任保障」保\n障。\n客戶買樓的時候,向銀行承做按揭,而銀行免費送贈火險,\n所以唔使買家居保險架!\n銀行免費送嘅火險保單,一般都係只包保障樓宇結構,並沒\n有包括家居財物及室內裝修嘅保障,不如我幫你盡快買返張\n家居寶,咁你嘅住所就會有全面嘅保障。\n如火險到期,可以加返落去張家居寶保單入面,咁就一張有\n齊全面嘅保障。\n(亦可以作為「開門磚」,同客戶再次接觸進行交叉銷售人壽\n或GI保險產品嘅機會。)\nConfidential\n18\n此為機密文件,及只作內部業務用途。請勿轉發。\n請注意:整個銷售過程及所有申請程序必須在香港進行",
          "content_tc": "保誠精選「家居寶」2022\n6. 注意事項\n其他事項\n1.\n「貴重財物」包括白金、黃金、珠寶首飾、錶、皮草、藝術品、古\n玩及攝影器材等。\n2.\n「欺詐網站」意指該網站屬欺詐性質,且已經由香港有關監管機構\n公開宣佈。\n3. 「持牌銀行」意指根據香港法例第155章《銀行業條例》於香港\n註冊的持牌銀行。\n4.\n「個人身份被盜用」意指未經授權而使用及/或非法使用您或您的\n家人的姓名或香港身份證號碼等個人資訊開立您或您的家人未授權\n的信用帳戶及/或銀行帳戶。\n5.\n「每件」意指一件、一對或一套物品。\n6.\n「家人」意指一般情況下與您永久同住的父母、兄弟姊妹、配偶、\n子女及親屬,如要為同住朋友投保,請在本申請表中列明。\n7. 就任何終止或更改本保單,按每保單收取港幣$400的最低保費。\nConfidential\n17\n此為機密文件,及只作內部業務用途。請勿轉發。\n請注意:整個銷售過程及所有申請程序必須在香港進行保誠精選「家居寶」2022\n7. 銷售術語\n· 不同客戶都有不同的需求,因此需要注意用詞和話術,特別\n是遇到異議時如何使用說話技巧應對\n點解要買家居保險呢?\n因為可以保障家居財物及室內裝修因意外時損毀所引致的維\n修費用;又或您及您的家人,因疏忽而導致第三者身體受傷\n或財物損失,而需負上的法律責任,都同樣獲得保障。\n客戶表示都住左咁耐,唔使買家居寶保險啦!\n唔好咁諗呀!最重要就係第三者法律責任保障,因為賠償金\n額可大可小,好難估計,所以一定要買保誠精選「家居寶」\n!如果你係業主,仲會有免費額外「業主法律責任保障」保\n障。\n客戶買樓的時候,向銀行承做按揭,而銀行免費送贈火險,\n所以唔使買家居保險架!\n銀行免費送嘅火險保單,一般都係只包保障樓宇結構,並沒\n有包括家居財物及室內裝修嘅保障,不如我幫你盡快買返張\n家居寶,咁你嘅住所就會有全面嘅保障。\n如火險到期,可以加返落去張家居寶保單入面,咁就一張有\n齊全面嘅保障。\n(亦可以作為「開門磚」,同客戶再次接觸進行交叉銷售人壽\n或GI保險產品嘅機會。)\nConfidential\n18\n此為機密文件,及只作內部業務用途。請勿轉發。\n請注意:整個銷售過程及所有申請程序必須在香港進行",
          "filename": "Home_Sales Toolkit_26 April 2022.pdf",
          "page_number": null,
          "score": 25.383589,
          "content_chunk": ""
        },
        {
          "id": "GI000061",
          "document_id": "GI000061",
          "title_name_en": "PRUchoice Home",
          "title_name_tc": "保誠精選「家居寶」",
          "content_en": "7. 銷售術語\n· 不同客戶都有不同的需求,因此需要注意用詞和話術,特別\n是遇到異議時如何使用說話技巧應對\n點解要買家居保險呢?\n因為可以保障家居財物及室內裝修因意外時損毀所引致的維\n修費用;又或您及您的家人,因疏忽而導致第三者身體受傷\n或財物損失,而需負上的法律責任,都同樣獲得保障。\n客戶表示都住左咁耐,唔使買家居寶保險啦!\n唔好咁諗呀!最重要就係第三者法律責任保障,因為賠償金\n額可大可小,好難估計,所以一定要買保誠精選「家居寶」\n!如果你係業主,仲會有免費額外「業主法律責任保障」保\n障。\n客戶買樓的時候,向銀行承做按揭,而銀行免費送贈火險,\n所以唔使買家居保險架!\n銀行免費送嘅火險保單,一般都係只包保障樓宇結構,並沒\n有包括家居財物及室內裝修嘅保障,不如我幫你盡快買返張\n家居寶,咁你嘅住所就會有全面嘅保障。\n如火險到期,可以加返落去張家居寶保單入面,咁就一張有\n齊全面嘅保障。\n(亦可以作為「開門磚」,同客戶再次接觸進行交叉銷售人壽\n或GI保險產品嘅機會。)\nConfidential\n18\n此為機密文件,及只作內部業務用途。請勿轉發。\n請注意:整個銷售過程及所有申請程序必須在香港進行保誠精選「家居寶」2022\n8. 常見問題\n保障範圍\n1.\n問\n保誠精選「家居寶」,是什麼保障及選擇?\n答\n2. 問\n保單是否設有最低保費?\n每份保單之最低及不可退回保費為港幣$400;或於保障期內,\n答\n有賠償紀錄,則並不獲得退回保費。\n3. 問\n誰人可以購買保誠精選「家居寶」?\n保單之「標準保障」〔Basic Cover〕,只合適於香港受保地址\n答\n內及整年居住的投保人,便可申請投保。\n而自選保障項目之「樓宇結構保障」〔Building Structure〕,\n必須該由受保地址之業主才可投保。\n4. 問\n如何計算樓宇面積?\n答\n若樓宇包括露台,是需要計算於受保住所內的面積。\n若樓宇包括花園、天台或平台,則不需計算於住所面積。\n5. 問\n兩間雙連單位的樓宇,打通為一間。可否購買一張保單?\n答\n可以,惟有關雙連單位打通項目,必須經屋宇署審批及按照打通\n後的總面積來購買保單。\n主要保障客戶在個人住宅之全面家居保險,保障家居因意外如颱\n風、火災、盜竊或水浸招致的家居財物損失及維修費用、因疏忽\n而引致第三者的法律責任,及特別保障在您及住戶身份下的額外\n風險。\n保障計劃分別為「小康之家」及「卓爾之家」,保費計算可以選\n擇以建築面積或實用面積投保或計算保費,保障項目及賠償額的\n詳情,請參閱「保障一覽表、保障範圍快覽及注意事項」。\nConfidential\n19\n此為機密文件,及只作內部業務用途。請勿轉發。\n請注意:整個銷售過程及所有申請程序必須在香港進行",
          "content_tc": "7. 銷售術語\n· 不同客戶都有不同的需求,因此需要注意用詞和話術,特別\n是遇到異議時如何使用說話技巧應對\n點解要買家居保險呢?\n因為可以保障家居財物及室內裝修因意外時損毀所引致的維\n修費用;又或您及您的家人,因疏忽而導致第三者身體受傷\n或財物損失,而需負上的法律責任,都同樣獲得保障。\n客戶表示都住左咁耐,唔使買家居寶保險啦!\n唔好咁諗呀!最重要就係第三者法律責任保障,因為賠償金\n額可大可小,好難估計,所以一定要買保誠精選「家居寶」\n!如果你係業主,仲會有免費額外「業主法律責任保障」保\n障。\n客戶買樓的時候,向銀行承做按揭,而銀行免費送贈火險,\n所以唔使買家居保險架!\n銀行免費送嘅火險保單,一般都係只包保障樓宇結構,並沒\n有包括家居財物及室內裝修嘅保障,不如我幫你盡快買返張\n家居寶,咁你嘅住所就會有全面嘅保障。\n如火險到期,可以加返落去張家居寶保單入面,咁就一張有\n齊全面嘅保障。\n(亦可以作為「開門磚」,同客戶再次接觸進行交叉銷售人壽\n或GI保險產品嘅機會。)\nConfidential\n18\n此為機密文件,及只作內部業務用途。請勿轉發。\n請注意:整個銷售過程及所有申請程序必須在香港進行保誠精選「家居寶」2022\n8. 常見問題\n保障範圍\n1.\n問\n保誠精選「家居寶」,是什麼保障及選擇?\n答\n2. 問\n保單是否設有最低保費?\n每份保單之最低及不可退回保費為港幣$400;或於保障期內,\n答\n有賠償紀錄,則並不獲得退回保費。\n3. 問\n誰人可以購買保誠精選「家居寶」?\n保單之「標準保障」〔Basic Cover〕,只合適於香港受保地址\n答\n內及整年居住的投保人,便可申請投保。\n而自選保障項目之「樓宇結構保障」〔Building Structure〕,\n必須該由受保地址之業主才可投保。\n4. 問\n如何計算樓宇面積?\n答\n若樓宇包括露台,是需要計算於受保住所內的面積。\n若樓宇包括花園、天台或平台,則不需計算於住所面積。\n5. 問\n兩間雙連單位的樓宇,打通為一間。可否購買一張保單?\n答\n可以,惟有關雙連單位打通項目,必須經屋宇署審批及按照打通\n後的總面積來購買保單。\n主要保障客戶在個人住宅之全面家居保險,保障家居因意外如颱\n風、火災、盜竊或水浸招致的家居財物損失及維修費用、因疏忽\n而引致第三者的法律責任,及特別保障在您及住戶身份下的額外\n風險。\n保障計劃分別為「小康之家」及「卓爾之家」,保費計算可以選\n擇以建築面積或實用面積投保或計算保費,保障項目及賠償額的\n詳情,請參閱「保障一覽表、保障範圍快覽及注意事項」。\nConfidential\n19\n此為機密文件,及只作內部業務用途。請勿轉發。\n請注意:整個銷售過程及所有申請程序必須在香港進行",
          "filename": "Home_Sales Toolkit_26 April 2022.pdf",
          "page_number": null,
          "score": 24.22782,
          "content_chunk": ""
        },
        {
          "id": "GI000061",
          "document_id": "GI000061",
          "title_name_en": "PRUchoice Home",
          "title_name_tc": "保誠精選「家居寶」",
          "content_en": "價值証明。\nd) 附加自選項目保障 - 樓宇結構保障\n如客戶最初只投保「基本保障」,其後提出附加「樓宇結構保障」,必須提\n供受保物業業主姓名(如與申請人不同)、投保額、按揭銀行或財務公司名稱\n(如適用),而投保額亦不少於港幣$500,000。\ne) 附加自選項目保障 - 家庭電器保養服務保障\n可以隨時提出,並不須要遞交任何文件。保費計算並不適用逐日收費及保單\n生效日起計不保障首30天內的電器故障。\n所有更改/附加保障的生效日,最早可以是通知日的當天;其後將會發出批\n單(Endorsement)核實,保費須逐日(Pro-rata basis)計算,並每張批單\n設有最低保費為港幣$50(需要再加IA Levy)。可透過電子查詢(eEnquiry)\n遞交申請及核保。\n3.\n問\n客戶續保保單,有何優惠?\n客戶於保單到期日或到期後六個月內續保時,不論有否索償記錄,「家居財\n物保障」項目會自動增加保額為港幣$50,000.00,最高累積為港幣\n$200,000.00。\nConfidential\n23\n答\n此為機密文件,及只作內部業務用途。請勿轉發。\n請注意:整個銷售過程及所有申請程序必須在香港進行保誠精選「家居寶」2022\n8. 常見問題\nePA\n1.\n問\n客戶在保障期內,需要更改通訊地址,如何處理?\n客戶可以登入myPrudential,選擇有關保單,在「選擇功能」\n點擊「更改保單資料」,並且輸入有關資料及遞交,當成功申請\n更改,有關文件稱之為「批單」,稍後便會上載到系統給予客戶\n查閱。\n答\n理財顧問可以透過AIS,在保單查詢中,選擇有關保單,在「選擇\n功能」點擊「更改保單資料」,並且輸入有關資料及遞交,當成\n功交申請更改,有關文件稱之為「批單」,稍後便會上載到AIS\n給予查閱。\n2.\n問\n客戶透過myPrudential,可以更改什麼項目?\n客戶可以登入myPrudential,可以更改項目如下;\n1) 更改保單資料,包括通訊地址,受保地址及受保物業面積\n答\n2)\n更改付款資料,即更改另一張信用咭付款;\n當完成遞交申請,保單更新需要三個工作天。\nConfidential\n24\n此為機密文件,及只作內部業務用途。請勿轉發。\n請注意:整個銷售過程及所有申請程序必須在香港進行",
          "content_tc": "價值証明。\nd) 附加自選項目保障 - 樓宇結構保障\n如客戶最初只投保「基本保障」,其後提出附加「樓宇結構保障」,必須提\n供受保物業業主姓名(如與申請人不同)、投保額、按揭銀行或財務公司名稱\n(如適用),而投保額亦不少於港幣$500,000。\ne) 附加自選項目保障 - 家庭電器保養服務保障\n可以隨時提出,並不須要遞交任何文件。保費計算並不適用逐日收費及保單\n生效日起計不保障首30天內的電器故障。\n所有更改/附加保障的生效日,最早可以是通知日的當天;其後將會發出批\n單(Endorsement)核實,保費須逐日(Pro-rata basis)計算,並每張批單\n設有最低保費為港幣$50(需要再加IA Levy)。可透過電子查詢(eEnquiry)\n遞交申請及核保。\n3.\n問\n客戶續保保單,有何優惠?\n客戶於保單到期日或到期後六個月內續保時,不論有否索償記錄,「家居財\n物保障」項目會自動增加保額為港幣$50,000.00,最高累積為港幣\n$200,000.00。\nConfidential\n23\n答\n此為機密文件,及只作內部業務用途。請勿轉發。\n請注意:整個銷售過程及所有申請程序必須在香港進行保誠精選「家居寶」2022\n8. 常見問題\nePA\n1.\n問\n客戶在保障期內,需要更改通訊地址,如何處理?\n客戶可以登入myPrudential,選擇有關保單,在「選擇功能」\n點擊「更改保單資料」,並且輸入有關資料及遞交,當成功申請\n更改,有關文件稱之為「批單」,稍後便會上載到系統給予客戶\n查閱。\n答\n理財顧問可以透過AIS,在保單查詢中,選擇有關保單,在「選擇\n功能」點擊「更改保單資料」,並且輸入有關資料及遞交,當成\n功交申請更改,有關文件稱之為「批單」,稍後便會上載到AIS\n給予查閱。\n2.\n問\n客戶透過myPrudential,可以更改什麼項目?\n客戶可以登入myPrudential,可以更改項目如下;\n1) 更改保單資料,包括通訊地址,受保地址及受保物業面積\n答\n2)\n更改付款資料,即更改另一張信用咭付款;\n當完成遞交申請,保單更新需要三個工作天。\nConfidential\n24\n此為機密文件,及只作內部業務用途。請勿轉發。\n請注意:整個銷售過程及所有申請程序必須在香港進行",
          "filename": "Home_Sales Toolkit_26 April 2022.pdf",
          "page_number": null,
          "score": 21.030445,
          "content_chunk": ""
        },
        {
          "id": "GI000061",
          "document_id": "GI000061",
          "title_name_en": "PRUchoice Home",
          "title_name_tc": "保誠精選「家居寶」",
          "content_en": "保誠精選「家居寶」2022\n8. 常見問題\nePA\n1.\n問\n客戶在保障期內,需要更改通訊地址,如何處理?\n客戶可以登入myPrudential,選擇有關保單,在「選擇功能」\n點擊「更改保單資料」,並且輸入有關資料及遞交,當成功申請\n更改,有關文件稱之為「批單」,稍後便會上載到系統給予客戶\n查閱。\n答\n理財顧問可以透過AIS,在保單查詢中,選擇有關保單,在「選擇\n功能」點擊「更改保單資料」,並且輸入有關資料及遞交,當成\n功交申請更改,有關文件稱之為「批單」,稍後便會上載到AIS\n給予查閱。\n2.\n問\n客戶透過myPrudential,可以更改什麼項目?\n客戶可以登入myPrudential,可以更改項目如下;\n1) 更改保單資料,包括通訊地址,受保地址及受保物業面積\n答\n2)\n更改付款資料,即更改另一張信用咭付款;\n當完成遞交申請,保單更新需要三個工作天。\nConfidential\n24\n此為機密文件,及只作內部業務用途。請勿轉發。\n請注意:整個銷售過程及所有申請程序必須在香港進行保誠精選「家居寶」2022\n8. 常見問題\n一次\n索償\n1.\n問\n若客户收到投訴有關漏水導致第三方的損失,應如何處理?\n客戶收到有關情況後,必須於31天內遞交索償申請,所需文件請\n參閱索償表格上的文件清單,而客戶亦應向其物業管理公司通報\n有關情況,及收集第三方追討文件,盡快遞交給理賠部處理,客\n戶並不應向第三方承諾/承擔任何責任或賠償方案。\n有關索償申請,如下:\n(1) 理財顧問可透過AIS「e索償」遞交申請及上載有關文件;\n答\n(2)客戶可以登入myPrudential帳戶,選擇有關保單,在「選\n擇功能」點擊「申請索償」,並且輸入有關資料及上載有關文件,\n當成功遞交後,客戶便會收到確認電郵。\n待我們收到有案後,一般處理及回覆時間為10個工作天。\n若受保住所內的水喉漏水,並需要拆除牆壁,才可以進行檢查情\n況,拆除牆壁的費用是否受到保障?\n2.\n問\n答\n如牆壁並沒有損毀,有關費用並不會獲得賠償。\nConfidential\n25\n此為機密文件,及只作內部業務用途。請勿轉發。\n請注意:整個銷售過程及所有申請程序必須在香港進行",
          "content_tc": "保誠精選「家居寶」2022\n8. 常見問題\nePA\n1.\n問\n客戶在保障期內,需要更改通訊地址,如何處理?\n客戶可以登入myPrudential,選擇有關保單,在「選擇功能」\n點擊「更改保單資料」,並且輸入有關資料及遞交,當成功申請\n更改,有關文件稱之為「批單」,稍後便會上載到系統給予客戶\n查閱。\n答\n理財顧問可以透過AIS,在保單查詢中,選擇有關保單,在「選擇\n功能」點擊「更改保單資料」,並且輸入有關資料及遞交,當成\n功交申請更改,有關文件稱之為「批單」,稍後便會上載到AIS\n給予查閱。\n2.\n問\n客戶透過myPrudential,可以更改什麼項目?\n客戶可以登入myPrudential,可以更改項目如下;\n1) 更改保單資料,包括通訊地址,受保地址及受保物業面積\n答\n2)\n更改付款資料,即更改另一張信用咭付款;\n當完成遞交申請,保單更新需要三個工作天。\nConfidential\n24\n此為機密文件,及只作內部業務用途。請勿轉發。\n請注意:整個銷售過程及所有申請程序必須在香港進行保誠精選「家居寶」2022\n8. 常見問題\n一次\n索償\n1.\n問\n若客户收到投訴有關漏水導致第三方的損失,應如何處理?\n客戶收到有關情況後,必須於31天內遞交索償申請,所需文件請\n參閱索償表格上的文件清單,而客戶亦應向其物業管理公司通報\n有關情況,及收集第三方追討文件,盡快遞交給理賠部處理,客\n戶並不應向第三方承諾/承擔任何責任或賠償方案。\n有關索償申請,如下:\n(1) 理財顧問可透過AIS「e索償」遞交申請及上載有關文件;\n答\n(2)客戶可以登入myPrudential帳戶,選擇有關保單,在「選\n擇功能」點擊「申請索償」,並且輸入有關資料及上載有關文件,\n當成功遞交後,客戶便會收到確認電郵。\n待我們收到有案後,一般處理及回覆時間為10個工作天。\n若受保住所內的水喉漏水,並需要拆除牆壁,才可以進行檢查情\n況,拆除牆壁的費用是否受到保障?\n2.\n問\n答\n如牆壁並沒有損毀,有關費用並不會獲得賠償。\nConfidential\n25\n此為機密文件,及只作內部業務用途。請勿轉發。\n請注意:整個銷售過程及所有申請程序必須在香港進行",
          "filename": "Home_Sales Toolkit_26 April 2022.pdf",
          "page_number": null,
          "score": 20.396744,
          "content_chunk": ""
        },
        {
          "id": "GI000061",
          "document_id": "GI000061",
          "title_name_en": "PRUchoice Home",
          "title_name_tc": "保誠精選「家居寶」",
          "content_en": "子查詢(eEnquiry),選擇「一般保險-產品/業務發展」,\n再點擊「產品/業務發展 個人保險(非醫療類別)」索取報價。\n2. 問\n於PRUeShop申請投保時,可以申請樓宇結構保障嗎?\n不可以,客戶必須遞交已填妥的申請表投保,可透過AIS 電子\n查詢(eEnquiry),選擇「一般保險-保單行政」,再點擊\n「個人保險(非醫療類別)」索取報價。\n答\n3.\n問\n理財顧問替客戶透過PRUeShop申請投保,保單最快可於何時生\n效?\n答\n保單最快可以即時生效或選擇指定生效日期,並且可以提早6個月\n前申請投保。\n4. 問\n透過PRUeShop成功投保,客戶如何收取保單?\n當投保申請被確認,客戶及理財顧問會收到確認電郵,電郵內會即\n時提供保單號碼,並列載保障範圍及詳細的保單條款。客戶亦可透\n答\n過收取的保單號碼到www.prudential.com.hk/scws/member 登\n入myPrudential帳戶,啟動有關帳戶以下載電子保單,查詢保單\n及更改保單資料。\nConfidential 22\n此為機密文件,及只作內部業務用途。請勿轉發。\n請注意:整個銷售過程及所有申請程序必須在香港進行保誠精選「家居寶」2022\n8. 常見問題\n保單行政\n一次\n1.\n問\n如在保險期內,是否可以更改保障計劃,如由「小康之家」改為「卓爾之\n家」,或由「卓爾之家」改為「小康之家」?\n答\n不可以,只可以在續保時提出更改。又或保單並未生效時,及在保險期內提\n出更改受保地址的住所面積限制,則除外。\n答\n2.\n問\n如在保險期內,客戶可以提出更改或附加保障嗎?\n可以在保險期內隨時提出更改,如下:\na) 更改受保地址\n必須提供新住所的地址、樓齡及住宅面積,以供核保。保費以住宅面積計算,\n可以選擇以建築面積(平方呎)或實用面積(平方呎),注意保障計劃的選擇,\n受到住所面積限制,如實用面積是1,000平方呎,則只可以選擇「卓爾之\n家」。\nb) 附加基本保障\n如客戶最初只投保「樓宇結構保障」,其後提出附加基本保障,必須提供住\n所面積,保費以住宅面積計算,可以選擇以建築面積(平方呎)或實用面積\n(平方呎),注意保障計劃的選擇,受到住所面積限制,如實用面積1,000平\n方呎,則只可以選擇「卓爾之家」。\nc) 附加自選項目保障 - 額外個人財物保障\n提供個人財物詳情及投保額,必須附上發票或價值証明。\nd) 附加自選項目保障 - 樓宇結構保障\n如客戶最初只投保「基本保障」,其後提出附加「樓宇結構保障」,必須提\n供受保物業業主姓名(如與申請人不同)、投保額、按揭銀行或財務公司名稱\n(如適用),而投保額亦不少於港幣$500,000。\ne) 附加自選項目保障 - 家庭電器保養服務保障\n可以隨時提出,並不須要遞交任何文件。保費計算並不適用逐日收費及保單\n生效日起計不保障首30天內的電器故障。\n所有更改/附加保障的生效日,最早可以是通知日的當天;其後將會發出批\n單(Endorsement)核實,保費須逐日(Pro-rata basis)計算,並每張批單\n設有最低保費為港幣$50(需要再加IA Levy)。可透過電子查詢(eEnquiry)\n遞交申請及核保。\n3.\n問\n客戶續保保單,有何優惠?\n客戶於保單到期日或到期後六個月內續保時,不論有否索償記錄,「家居財\n物保障」項目會自動增加保額為港幣$50,000.00,最高累積為港幣\n$200,000.00。\nConfidential\n23\n答\n此為機密文件,及只作內部業務用途。請勿轉發。\n請注意:整個銷售過程及所有申請程序必須在香港進行",
          "content_tc": "子查詢(eEnquiry),選擇「一般保險-產品/業務發展」,\n再點擊「產品/業務發展 個人保險(非醫療類別)」索取報價。\n2. 問\n於PRUeShop申請投保時,可以申請樓宇結構保障嗎?\n不可以,客戶必須遞交已填妥的申請表投保,可透過AIS 電子\n查詢(eEnquiry),選擇「一般保險-保單行政」,再點擊\n「個人保險(非醫療類別)」索取報價。\n答\n3.\n問\n理財顧問替客戶透過PRUeShop申請投保,保單最快可於何時生\n效?\n答\n保單最快可以即時生效或選擇指定生效日期,並且可以提早6個月\n前申請投保。\n4. 問\n透過PRUeShop成功投保,客戶如何收取保單?\n當投保申請被確認,客戶及理財顧問會收到確認電郵,電郵內會即\n時提供保單號碼,並列載保障範圍及詳細的保單條款。客戶亦可透\n答\n過收取的保單號碼到www.prudential.com.hk/scws/member 登\n入myPrudential帳戶,啟動有關帳戶以下載電子保單,查詢保單\n及更改保單資料。\nConfidential 22\n此為機密文件,及只作內部業務用途。請勿轉發。\n請注意:整個銷售過程及所有申請程序必須在香港進行保誠精選「家居寶」2022\n8. 常見問題\n保單行政\n一次\n1.\n問\n如在保險期內,是否可以更改保障計劃,如由「小康之家」改為「卓爾之\n家」,或由「卓爾之家」改為「小康之家」?\n答\n不可以,只可以在續保時提出更改。又或保單並未生效時,及在保險期內提\n出更改受保地址的住所面積限制,則除外。\n答\n2.\n問\n如在保險期內,客戶可以提出更改或附加保障嗎?\n可以在保險期內隨時提出更改,如下:\na) 更改受保地址\n必須提供新住所的地址、樓齡及住宅面積,以供核保。保費以住宅面積計算,\n可以選擇以建築面積(平方呎)或實用面積(平方呎),注意保障計劃的選擇,\n受到住所面積限制,如實用面積是1,000平方呎,則只可以選擇「卓爾之\n家」。\nb) 附加基本保障\n如客戶最初只投保「樓宇結構保障」,其後提出附加基本保障,必須提供住\n所面積,保費以住宅面積計算,可以選擇以建築面積(平方呎)或實用面積\n(平方呎),注意保障計劃的選擇,受到住所面積限制,如實用面積1,000平\n方呎,則只可以選擇「卓爾之家」。\nc) 附加自選項目保障 - 額外個人財物保障\n提供個人財物詳情及投保額,必須附上發票或價值証明。\nd) 附加自選項目保障 - 樓宇結構保障\n如客戶最初只投保「基本保障」,其後提出附加「樓宇結構保障」,必須提\n供受保物業業主姓名(如與申請人不同)、投保額、按揭銀行或財務公司名稱\n(如適用),而投保額亦不少於港幣$500,000。\ne) 附加自選項目保障 - 家庭電器保養服務保障\n可以隨時提出,並不須要遞交任何文件。保費計算並不適用逐日收費及保單\n生效日起計不保障首30天內的電器故障。\n所有更改/附加保障的生效日,最早可以是通知日的當天;其後將會發出批\n單(Endorsement)核實,保費須逐日(Pro-rata basis)計算,並每張批單\n設有最低保費為港幣$50(需要再加IA Levy)。可透過電子查詢(eEnquiry)\n遞交申請及核保。\n3.\n問\n客戶續保保單,有何優惠?\n客戶於保單到期日或到期後六個月內續保時,不論有否索償記錄,「家居財\n物保障」項目會自動增加保額為港幣$50,000.00,最高累積為港幣\n$200,000.00。\nConfidential\n23\n答\n此為機密文件,及只作內部業務用途。請勿轉發。\n請注意:整個銷售過程及所有申請程序必須在香港進行",
          "filename": "Home_Sales Toolkit_26 April 2022.pdf",
          "page_number": null,
          "score": 19.513695,
          "content_chunk": ""
        },
        {
          "id": "GI000061",
          "document_id": "GI000061",
          "title_name_en": "PRUchoice Home",
          "title_name_tc": "保誠精選「家居寶」",
          "content_en": "保存原有配件、使用指南、說明書及保證書,並在有需要時提供作檢\n查之用,直至索償完成\n■ 手提電話/任何具手提電話功能的電子產品,及其所有配件均不受保障\n12.2.2 滲水至第三者單單位情況\n▪\n在滲水出現時,就受保人可能需要負上的法律責任,即因疏忽而導致第\n三者損失,作出處理及賠償\n■ 當發現滲水,不論第三者有否追討賠償,受保人都應立即填寫索償表格\n並交予我們作通知,在得悉有關情況後,我們將為賠償事宜作出考慮與\n安排\n■ 受保人應立即找出滲水的源頭,及在有需要時安排維修人員維修\n■ 如收到索償信、律師信或法庭傳票等,請勿私自回覆,並應立即交予我\n們\n■ 請勿私自向任何第三者承認責任或作出賠償承諾\n■ 如第三者向受保人追討賠償,請要求第三者以書面形式列明其要求。當\n受保人收到第三者的書面索償,請立即交予我們。如有需要,我們將直\n接聯絡第三者\n12.2.3 遺失現金及信用卡被盜用保障\n■ 若遺失信用卡,請即通知信用卡發行機構\n■ 必須於發現後二十四小時內向警方報告\nConfidential 42\n此為機密文件,及只作內部業務用途。請勿轉發。\n請注意:整個銷售過程及所有申請程序必須在香港進行保誠精選「家居寶」2022\n12. 索償\n12.2 索償項目\n12.2.4 個人財物損毀保障\n■ 在損毀財物能夠被修理的情況下,賠償修理的開支\n■ 請保存損毀財物的原有配件、使用指南、說明書及保證書,並在有需要\n時提供作檢查之用,直至索償完成\n■ 手提電話/任何具手提電話功能的電子產品,及其所有配件均不受保障\n■ 任何於清潔、修改、維修、翻新、保養或漂染過程中,或錯誤使用、違\n反製造商指引下使用、內在缺陷、物料、圖樣或規格上的設計錯誤、或\n逐漸變壞及變型等所導致的損毀是不受保障的\n12.2.5 家居財物損毀保障\n■ 就家居財物損毀作出賠償,惟不包括樓宇部分、固定裝置及配置(除非\n是由受保人自行添置的室內裝修,詳情請參考下列註釋)\n■ 家居財物的損毀,應由意外性質事件所導致。因此,若因1. 自然損耗2.\n蛀蟲3.害蟲4.昆蟲5.寵物6.潮濕7.生鏽8.腐爛9.腐蝕10.發霉11.濕氣12.\n陽光或大氣作用及13. 以漸進原因所導致或促成的損毀,是不獲保障的\n■ 當意外性質事件發生時,應立即阻止,減低損失\n■ 因電力或機械故障、錯亂、負荷過多或不足所導致的電器損毀是不獲保\n障的\n▪\n玻璃物件(包括鏡、陶瓷器、陶器、土器及水晶擺設)因火災、爆炸、\n爆竊或盜竊而被打碎是獲保障的\n■ 若室內裝修、固定裝置及配置由受保人自行添置,皆可被視作家居財物\n。請提供自行添置這些室內裝修、固定裝置及配置的證明,例如原有安\n裝收據正本等。否則,這些物件將被視作樓宇一部分,並只會在保單中\n另有投保樓宇結構保障項目的情況下受保\n▪\n不保障手提電話損毀,除非受保人已支付額外保費,特別為該手提電話\n投保\n■ 任何於清潔、修改、維修、翻新、保養或漂染過程中,或錯誤使用、違\n反製造商指引下使用、內在缺陷、物料、圖樣或規格上的設計錯誤、或\n逐漸變壞及變型等所導致的損毀是不受保障的\nConfidential 43\n此為機密文件,及只作內部業務用途。請勿轉發。\n請注意:整個銷售過程及所有申請程序必須在香港進行",
          "content_tc": "保存原有配件、使用指南、說明書及保證書,並在有需要時提供作檢\n查之用,直至索償完成\n■ 手提電話/任何具手提電話功能的電子產品,及其所有配件均不受保障\n12.2.2 滲水至第三者單單位情況\n▪\n在滲水出現時,就受保人可能需要負上的法律責任,即因疏忽而導致第\n三者損失,作出處理及賠償\n■ 當發現滲水,不論第三者有否追討賠償,受保人都應立即填寫索償表格\n並交予我們作通知,在得悉有關情況後,我們將為賠償事宜作出考慮與\n安排\n■ 受保人應立即找出滲水的源頭,及在有需要時安排維修人員維修\n■ 如收到索償信、律師信或法庭傳票等,請勿私自回覆,並應立即交予我\n們\n■ 請勿私自向任何第三者承認責任或作出賠償承諾\n■ 如第三者向受保人追討賠償,請要求第三者以書面形式列明其要求。當\n受保人收到第三者的書面索償,請立即交予我們。如有需要,我們將直\n接聯絡第三者\n12.2.3 遺失現金及信用卡被盜用保障\n■ 若遺失信用卡,請即通知信用卡發行機構\n■ 必須於發現後二十四小時內向警方報告\nConfidential 42\n此為機密文件,及只作內部業務用途。請勿轉發。\n請注意:整個銷售過程及所有申請程序必須在香港進行保誠精選「家居寶」2022\n12. 索償\n12.2 索償項目\n12.2.4 個人財物損毀保障\n■ 在損毀財物能夠被修理的情況下,賠償修理的開支\n■ 請保存損毀財物的原有配件、使用指南、說明書及保證書,並在有需要\n時提供作檢查之用,直至索償完成\n■ 手提電話/任何具手提電話功能的電子產品,及其所有配件均不受保障\n■ 任何於清潔、修改、維修、翻新、保養或漂染過程中,或錯誤使用、違\n反製造商指引下使用、內在缺陷、物料、圖樣或規格上的設計錯誤、或\n逐漸變壞及變型等所導致的損毀是不受保障的\n12.2.5 家居財物損毀保障\n■ 就家居財物損毀作出賠償,惟不包括樓宇部分、固定裝置及配置(除非\n是由受保人自行添置的室內裝修,詳情請參考下列註釋)\n■ 家居財物的損毀,應由意外性質事件所導致。因此,若因1. 自然損耗2.\n蛀蟲3.害蟲4.昆蟲5.寵物6.潮濕7.生鏽8.腐爛9.腐蝕10.發霉11.濕氣12.\n陽光或大氣作用及13. 以漸進原因所導致或促成的損毀,是不獲保障的\n■ 當意外性質事件發生時,應立即阻止,減低損失\n■ 因電力或機械故障、錯亂、負荷過多或不足所導致的電器損毀是不獲保\n障的\n▪\n玻璃物件(包括鏡、陶瓷器、陶器、土器及水晶擺設)因火災、爆炸、\n爆竊或盜竊而被打碎是獲保障的\n■ 若室內裝修、固定裝置及配置由受保人自行添置,皆可被視作家居財物\n。請提供自行添置這些室內裝修、固定裝置及配置的證明,例如原有安\n裝收據正本等。否則,這些物件將被視作樓宇一部分,並只會在保單中\n另有投保樓宇結構保障項目的情況下受保\n▪\n不保障手提電話損毀,除非受保人已支付額外保費,特別為該手提電話\n投保\n■ 任何於清潔、修改、維修、翻新、保養或漂染過程中,或錯誤使用、違\n反製造商指引下使用、內在缺陷、物料、圖樣或規格上的設計錯誤、或\n逐漸變壞及變型等所導致的損毀是不受保障的\nConfidential 43\n此為機密文件,及只作內部業務用途。請勿轉發。\n請注意:整個銷售過程及所有申請程序必須在香港進行",
          "filename": "Home_Sales Toolkit_26 April 2022.pdf",
          "page_number": null,
          "score": 19.24776,
          "content_chunk": ""
        },
        {
          "id": "GI000061",
          "document_id": "GI000061",
          "title_name_en": "PRUchoice Home",
          "title_name_tc": "保誠精選「家居寶」",
          "content_en": "保誠精選「家居寶」2022\n8. 常見問題\n一次\n索償\n1.\n問\n若客户收到投訴有關漏水導致第三方的損失,應如何處理?\n客戶收到有關情況後,必須於31天內遞交索償申請,所需文件請\n參閱索償表格上的文件清單,而客戶亦應向其物業管理公司通報\n有關情況,及收集第三方追討文件,盡快遞交給理賠部處理,客\n戶並不應向第三方承諾/承擔任何責任或賠償方案。\n有關索償申請,如下:\n(1) 理財顧問可透過AIS「e索償」遞交申請及上載有關文件;\n答\n(2)客戶可以登入myPrudential帳戶,選擇有關保單,在「選\n擇功能」點擊「申請索償」,並且輸入有關資料及上載有關文件,\n當成功遞交後,客戶便會收到確認電郵。\n待我們收到有案後,一般處理及回覆時間為10個工作天。\n若受保住所內的水喉漏水,並需要拆除牆壁,才可以進行檢查情\n況,拆除牆壁的費用是否受到保障?\n2.\n問\n答\n如牆壁並沒有損毀,有關費用並不會獲得賠償。\nConfidential\n25\n此為機密文件,及只作內部業務用途。請勿轉發。\n請注意:整個銷售過程及所有申請程序必須在香港進行保誠精選「家居寶」2022\n9. 產品指引\n回=\n一次\n9.1 申請資格\n✓\n投保人必須年滿18歲而是固定居住於香港境內的受保地址,申請\n人的身份如下:\n· 租戶\n· 業主\n✓\n受保地址必須是香港境內,而樓宇類別\n· 政府樓宇:可於「香港房屋委員會及房屋署」或「香港房屋協會」\n的網頁在「尋找屋邨」,搜尋政府樓宇資料\n· 私人樓宇:可於各地產網頁內搜尋資料\n· 村屋:可向客戶收集資料\n✓\n產品分類\n•\n基本保障,計劃分別\n❑\n小康之家\n❑\n卓爾之家\n•\n自選保障,可附加以下項目:\n❑\n「額外個人財物」:例如價值港幣50,000的手錶或鑽戒等\n❑\n「樓宇結構」:為受保住所的樓宇結構,提供「全險」的保障\n❑\n「家庭電器保養服務」:為受保住所內使用的「家庭電器」,只\n限電視機(不包括顯示屏)、雪櫃、洗衣機、乾衣機、冷氣機、\n藍光光碟/鐳射影碟機及微波爐。\nConfidential 26\n此為機密文件,及只作內部業務用途。請勿轉發。\n請注意:整個銷售過程及所有申請程序必須在香港進行",
          "content_tc": "保誠精選「家居寶」2022\n8. 常見問題\n一次\n索償\n1.\n問\n若客户收到投訴有關漏水導致第三方的損失,應如何處理?\n客戶收到有關情況後,必須於31天內遞交索償申請,所需文件請\n參閱索償表格上的文件清單,而客戶亦應向其物業管理公司通報\n有關情況,及收集第三方追討文件,盡快遞交給理賠部處理,客\n戶並不應向第三方承諾/承擔任何責任或賠償方案。\n有關索償申請,如下:\n(1) 理財顧問可透過AIS「e索償」遞交申請及上載有關文件;\n答\n(2)客戶可以登入myPrudential帳戶,選擇有關保單,在「選\n擇功能」點擊「申請索償」,並且輸入有關資料及上載有關文件,\n當成功遞交後,客戶便會收到確認電郵。\n待我們收到有案後,一般處理及回覆時間為10個工作天。\n若受保住所內的水喉漏水,並需要拆除牆壁,才可以進行檢查情\n況,拆除牆壁的費用是否受到保障?\n2.\n問\n答\n如牆壁並沒有損毀,有關費用並不會獲得賠償。\nConfidential\n25\n此為機密文件,及只作內部業務用途。請勿轉發。\n請注意:整個銷售過程及所有申請程序必須在香港進行保誠精選「家居寶」2022\n9. 產品指引\n回=\n一次\n9.1 申請資格\n✓\n投保人必須年滿18歲而是固定居住於香港境內的受保地址,申請\n人的身份如下:\n· 租戶\n· 業主\n✓\n受保地址必須是香港境內,而樓宇類別\n· 政府樓宇:可於「香港房屋委員會及房屋署」或「香港房屋協會」\n的網頁在「尋找屋邨」,搜尋政府樓宇資料\n· 私人樓宇:可於各地產網頁內搜尋資料\n· 村屋:可向客戶收集資料\n✓\n產品分類\n•\n基本保障,計劃分別\n❑\n小康之家\n❑\n卓爾之家\n•\n自選保障,可附加以下項目:\n❑\n「額外個人財物」:例如價值港幣50,000的手錶或鑽戒等\n❑\n「樓宇結構」:為受保住所的樓宇結構,提供「全險」的保障\n❑\n「家庭電器保養服務」:為受保住所內使用的「家庭電器」,只\n限電視機(不包括顯示屏)、雪櫃、洗衣機、乾衣機、冷氣機、\n藍光光碟/鐳射影碟機及微波爐。\nConfidential 26\n此為機密文件,及只作內部業務用途。請勿轉發。\n請注意:整個銷售過程及所有申請程序必須在香港進行",
          "filename": "Home_Sales Toolkit_26 April 2022.pdf",
          "page_number": null,
          "score": 19.189999,
          "content_chunk": ""
        },
        {
          "id": "GI000061",
          "document_id": "GI000061",
          "title_name_en": "PRUchoice Home",
          "title_name_tc": "保誠精選「家居寶」",
          "content_en": "保誠精選「家居寶」2022\n9. 產品指引\n參考自負金額\n✓\n適用於樓齡40年以下的村屋:\n基本保障\n每次每宗損失的自負金額\n項目一:家居財物保障\n適用於項目一、五及九:\n由水濕引致的損失的自負金額為港幣$3,000或損\n失評估總值10%,以較高者為準。\n項目五:第三者法律責任保障\n自選保障\n項目九:樓宇結構保障\n適用於項目一:\n因遭爆竊引致的損失的自負金額為港幣$3,000或\n損失評估總值10%,以較高者為準。\n注意:\n1)受保地址是由5座村屋或以上組成一個屋苑或附近有5間以上的村屋。\n2)並設有物業管理處或安裝防盜系統。\n3)連同受保地址的相片(包括外觀及附近環境)。\n4)於此類個別報價核保的申請,公司最終有機會要求附加特別條款及/或徵收額外保\n費/未能接納有關申請。\nConfidential\n29\n此為機密文件,及只作內部業務用途。請勿轉發。\n請注意:整個銷售過程及所有申請程序必須在香港進行保誠精選「家居寶」2022\n9. 產品指引\n回覆電子查詢及報價單參考範本\n訊息內容(來自 GIEB)\n回覆者:\nSample\n訊息日期:17/02/2022 09:49\nQuotation 800000\nHome insurance 家居寶\n已上傳文件:\n-00\n. 8000000\nKY.pdf\nWell received your information and we are pleased to provide the quotation of PRUChoice\nHome Insurance for your client's consideration. If client accepts the attached quotation,\nplease provide the signed PRUChoice Home application form (PIL:GI000061) and this\nquotation via eEnquiry (*Hard copy is NOT required) for policy issuance.\n**** Please note that we do not cover the glass house at the roof and ground floor in the\nquotation ***\n我們已收到您的資料,並為您的客戶提供保誠精選家居寶的報價。如客戶接受附件中的報價,請\n透過電子查詢遞交填妥的保誠精選「家居寶」投保書(PIL: GI000061)及此報價(*無需遞交正\n本),以發出保單。\nPrudential General Insurance Hong Kong Limited\nPRU choice HOME\nSample\nTO BE ADVISED\nHONG KONG\nPRUDENTIAL\n保 誠 保險!\nIssue Date : 17/02/2022\nQuotation Number\nPolicy Year : 2022\nAccount Code\nOriginal\nQuotation\nPeriod of Insurance: 17/02/2022 To 16/02/2023\n(To be advised)\nName of the Insured\nTO BE ADVISED\nInsured Premises\n新界元朗八鄉上章村1 (AOB: 25Y)\nGross Floor Area\n:\nSaleable Area\n1,501 - 2,000 SQUARE FEET\nClass of Construction\n:\nCLASS 1\nPlan\n:\nPremier Plan\nName of Mortgagee\n:\nLoan Number\n:\nN/A\nN/A\nInsurance Details\nSection\nMaximum Limits\nI\nHousehold Contents\nHKD\n1,500,000.00\n- Furniture Household Goods or Appliance (Per item)\nHKD\n150,000.00\n=\nPersonal Effects Worldwide Cover\nHKD\n20,000.00\nLoss of Personal Money, Unauthorized Use of Credit Card and\nOnline Protection\nHKD\n64,000.00\nIV\nLoss of Personal Documents\nHKD\n2,500.00\nV\nThird Party Legal Liability\nHKD\n15,000,000.00\nVI\nFamily Personal Accident\nHKD\n200,000.00\nVII\nNew Home Transition Period Protection\nAs Per Policy\nVIII\nPersonal Effects Extra\nNot Insured\nIX\nBuilding Structure\nNot Insured\nx\nHome Appliance Warranty Service\nNot Insured\nXI\nOverseas Domestic Helper\nNot Applicable\nExcess Clause(s):\n·\nHKD5,000.00 or 10% of the adjusted loss whichever is the greater in respect of water damage for each and every loss\n(applicable to Sections I & IX)\n·\n每次及每宗因水濕引致的損失的自負金額為港幣$5,000或損失評估總值10%,以較高者為準(適用於项目一及九)\nHKD5,000.00 or 10% of the adjusted loss whichever is the greater in respect of third party water damage for each and\nevery loss (applicable to Section V)\nSample\n每次及每宗因水濕引致第三者損失的自負金額為港幣$5,000或損失評估總值10%,以較高者為準(適用於项目五)\n·\nHKD5,000.00 or 10% of the adjusted loss whichever is the greater in respect of burglary for each and every loss\n(applicable to Section I)\n每次及每宗因遭爆腐引致的損失的自負金額為港幣$5,000或損失評估 值10%,以較高者為準(適用於项目一)\nThe above quotation is subject to the following conditions 以 上级個是基於下列修數及細則所發放:\n.\nClass One Construction for situation of risks;\n此受保地址屬第一類建築\n.\nSubject to no claims history in the past 3 years;\n此受保地址過去三年沒有索償記錄\n·\nSubject to no sub-divided units and illegal structure;\n此受保地址沒有板間房(創房)及非法結構\n·\nSubject to Communicable Disease/COVID-19/Pandemic Exclusion Clause-T5\n本保單受傳染病/COVID-19/大流行病不保條款約束。\n·\nSubject to PRUchoice Home Insurance Policy standard terms and conditions;\n一切依據保誠精選家居寶保單所載的條款及條件\n·\nSubject to minimum policy premium HKD400.00;\n本公司將按每保單收取港幣400元的最低保費\nSubject to satisfactory application form;\n投保時須遞交已填妥之申請表格\n.\nThis is an indicative quotation. This quote is valid for 30 days from issue date\n本報價之有效期為發出日期起計30日\nCollection of Levy by the Insurance Authority (\"IA)\nLevy collected by the Insurance Authority (if any) has been imposed on this policy at the application rate and would be\nremitted in accordance with the prescribed arrangements. For further information, please visit\nhttp:/www.prudential.com.hk/levy or www.ia.org.hk/tc/levy. If you do not pay the overdue levy timely, the Insurance\nAuthority (\"IA\") may, according to the law, impose on the policyholder a penalty and may recover the outstanding levy\nas a civil debt due to the IA.\n保險業監管局(「保險局」)收取的繳費\n保險業監管局(「保監局」)已按適用費率對此保單微收微費,有開徵費將按照訂明安排匯付。如需更多資訊,請瀏覽\nhttp://www.prudential.com.hk/levy 或 www.ia.org.hkotc/levy。 若 罔下未能依時清繳過期微費,保險業監管局(「保監局\n」)可根據法例向其施加罰歉,亦可循民事程序追討欠付的微量。\nDate of Quotation\n: 17/02/2022\nGross Premium\n: HKD\n2,410.00\nLevy (0.100%)\n: HKD\n2.41\nTotal Premium\n: HKD\n2,412.41\nShould you have any queries, please contact your Financial Consultant at 39487659 or us.\nFor and on behalf of\nPrudential General Insurance Hong Kong Limited\nAuthorized Signature\n(This is computer-generated and no counter-signature or stamp is required.)\nPage 1 of 2\nFGD2018A\n04/21\nPrudential General Insurance Hong Kong Limited BEIM A 1 218]\n3/F, Berkshire House, 25 Westlands Road, Quarry Bay, Hong Kong Mu El\n號柏克大廈3樓T +052 2977 3000 F+ 852 2977 1266\nwww.prudential.com.hk Amember of Prudentialple group ABRHMEN\nInpgbokye\nPage 2 of 2\nFGD2018A\n04/21\n遞交投保申請\n✓\n如客戶接受報價,請透過電子查詢遞交填妥的保誠精選「家居寶」\n投保書(PIL: GI000061)及報價(*無需遞交正本),以安排發出保單\nConfidential 30\n此為機密文件,及只作內部業務用途。請勿轉發。\n請注意:整個銷售過程及所有申請程序必須在香港進行",
          "content_tc": "保誠精選「家居寶」2022\n9. 產品指引\n參考自負金額\n✓\n適用於樓齡40年以下的村屋:\n基本保障\n每次每宗損失的自負金額\n項目一:家居財物保障\n適用於項目一、五及九:\n由水濕引致的損失的自負金額為港幣$3,000或損\n失評估總值10%,以較高者為準。\n項目五:第三者法律責任保障\n自選保障\n項目九:樓宇結構保障\n適用於項目一:\n因遭爆竊引致的損失的自負金額為港幣$3,000或\n損失評估總值10%,以較高者為準。\n注意:\n1)受保地址是由5座村屋或以上組成一個屋苑或附近有5間以上的村屋。\n2)並設有物業管理處或安裝防盜系統。\n3)連同受保地址的相片(包括外觀及附近環境)。\n4)於此類個別報價核保的申請,公司最終有機會要求附加特別條款及/或徵收額外保\n費/未能接納有關申請。\nConfidential\n29\n此為機密文件,及只作內部業務用途。請勿轉發。\n請注意:整個銷售過程及所有申請程序必須在香港進行保誠精選「家居寶」2022\n9. 產品指引\n回覆電子查詢及報價單參考範本\n訊息內容(來自 GIEB)\n回覆者:\nSample\n訊息日期:17/02/2022 09:49\nQuotation 800000\nHome insurance 家居寶\n已上傳文件:\n-00\n. 8000000\nKY.pdf\nWell received your information and we are pleased to provide the quotation of PRUChoice\nHome Insurance for your client's consideration. If client accepts the attached quotation,\nplease provide the signed PRUChoice Home application form (PIL:GI000061) and this\nquotation via eEnquiry (*Hard copy is NOT required) for policy issuance.\n**** Please note that we do not cover the glass house at the roof and ground floor in the\nquotation ***\n我們已收到您的資料,並為您的客戶提供保誠精選家居寶的報價。如客戶接受附件中的報價,請\n透過電子查詢遞交填妥的保誠精選「家居寶」投保書(PIL: GI000061)及此報價(*無需遞交正\n本),以發出保單。\nPrudential General Insurance Hong Kong Limited\nPRU choice HOME\nSample\nTO BE ADVISED\nHONG KONG\nPRUDENTIAL\n保 誠 保險!\nIssue Date : 17/02/2022\nQuotation Number\nPolicy Year : 2022\nAccount Code\nOriginal\nQuotation\nPeriod of Insurance: 17/02/2022 To 16/02/2023\n(To be advised)\nName of the Insured\nTO BE ADVISED\nInsured Premises\n新界元朗八鄉上章村1 (AOB: 25Y)\nGross Floor Area\n:\nSaleable Area\n1,501 - 2,000 SQUARE FEET\nClass of Construction\n:\nCLASS 1\nPlan\n:\nPremier Plan\nName of Mortgagee\n:\nLoan Number\n:\nN/A\nN/A\nInsurance Details\nSection\nMaximum Limits\nI\nHousehold Contents\nHKD\n1,500,000.00\n- Furniture Household Goods or Appliance (Per item)\nHKD\n150,000.00\n=\nPersonal Effects Worldwide Cover\nHKD\n20,000.00\nLoss of Personal Money, Unauthorized Use of Credit Card and\nOnline Protection\nHKD\n64,000.00\nIV\nLoss of Personal Documents\nHKD\n2,500.00\nV\nThird Party Legal Liability\nHKD\n15,000,000.00\nVI\nFamily Personal Accident\nHKD\n200,000.00\nVII\nNew Home Transition Period Protection\nAs Per Policy\nVIII\nPersonal Effects Extra\nNot Insured\nIX\nBuilding Structure\nNot Insured\nx\nHome Appliance Warranty Service\nNot Insured\nXI\nOverseas Domestic Helper\nNot Applicable\nExcess Clause(s):\n·\nHKD5,000.00 or 10% of the adjusted loss whichever is the greater in respect of water damage for each and every loss\n(applicable to Sections I & IX)\n·\n每次及每宗因水濕引致的損失的自負金額為港幣$5,000或損失評估總值10%,以較高者為準(適用於项目一及九)\nHKD5,000.00 or 10% of the adjusted loss whichever is the greater in respect of third party water damage for each and\nevery loss (applicable to Section V)\nSample\n每次及每宗因水濕引致第三者損失的自負金額為港幣$5,000或損失評估總值10%,以較高者為準(適用於项目五)\n·\nHKD5,000.00 or 10% of the adjusted loss whichever is the greater in respect of burglary for each and every loss\n(applicable to Section I)\n每次及每宗因遭爆腐引致的損失的自負金額為港幣$5,000或損失評估 值10%,以較高者為準(適用於项目一)\nThe above quotation is subject to the following conditions 以 上级個是基於下列修數及細則所發放:\n.\nClass One Construction for situation of risks;\n此受保地址屬第一類建築\n.\nSubject to no claims history in the past 3 years;\n此受保地址過去三年沒有索償記錄\n·\nSubject to no sub-divided units and illegal structure;\n此受保地址沒有板間房(創房)及非法結構\n·\nSubject to Communicable Disease/COVID-19/Pandemic Exclusion Clause-T5\n本保單受傳染病/COVID-19/大流行病不保條款約束。\n·\nSubject to PRUchoice Home Insurance Policy standard terms and conditions;\n一切依據保誠精選家居寶保單所載的條款及條件\n·\nSubject to minimum policy premium HKD400.00;\n本公司將按每保單收取港幣400元的最低保費\nSubject to satisfactory application form;\n投保時須遞交已填妥之申請表格\n.\nThis is an indicative quotation. This quote is valid for 30 days from issue date\n本報價之有效期為發出日期起計30日\nCollection of Levy by the Insurance Authority (\"IA)\nLevy collected by the Insurance Authority (if any) has been imposed on this policy at the application rate and would be\nremitted in accordance with the prescribed arrangements. For further information, please visit\nhttp:/www.prudential.com.hk/levy or www.ia.org.hk/tc/levy. If you do not pay the overdue levy timely, the Insurance\nAuthority (\"IA\") may, according to the law, impose on the policyholder a penalty and may recover the outstanding levy\nas a civil debt due to the IA.\n保險業監管局(「保險局」)收取的繳費\n保險業監管局(「保監局」)已按適用費率對此保單微收微費,有開徵費將按照訂明安排匯付。如需更多資訊,請瀏覽\nhttp://www.prudential.com.hk/levy 或 www.ia.org.hkotc/levy。 若 罔下未能依時清繳過期微費,保險業監管局(「保監局\n」)可根據法例向其施加罰歉,亦可循民事程序追討欠付的微量。\nDate of Quotation\n: 17/02/2022\nGross Premium\n: HKD\n2,410.00\nLevy (0.100%)\n: HKD\n2.41\nTotal Premium\n: HKD\n2,412.41\nShould you have any queries, please contact your Financial Consultant at 39487659 or us.\nFor and on behalf of\nPrudential General Insurance Hong Kong Limited\nAuthorized Signature\n(This is computer-generated and no counter-signature or stamp is required.)\nPage 1 of 2\nFGD2018A\n04/21\nPrudential General Insurance Hong Kong Limited BEIM A 1 218]\n3/F, Berkshire House, 25 Westlands Road, Quarry Bay, Hong Kong Mu El\n號柏克大廈3樓T +052 2977 3000 F+ 852 2977 1266\nwww.prudential.com.hk Amember of Prudentialple group ABRHMEN\nInpgbokye\nPage 2 of 2\nFGD2018A\n04/21\n遞交投保申請\n✓\n如客戶接受報價,請透過電子查詢遞交填妥的保誠精選「家居寶」\n投保書(PIL: GI000061)及報價(*無需遞交正本),以安排發出保單\nConfidential 30\n此為機密文件,及只作內部業務用途。請勿轉發。\n請注意:整個銷售過程及所有申請程序必須在香港進行",
          "filename": "Home_Sales Toolkit_26 April 2022.pdf",
          "page_number": null,
          "score": 18.980036,
          "content_chunk": ""
        },
        {
          "id": "GI000061",
          "document_id": "GI000061",
          "title_name_en": "PRUchoice Home",
          "title_name_tc": "保誠精選「家居寶」",
          "content_en": "保誠精選「家居寶」2022\n12. 索償\n12.1 客戶可經 eClaims申請索償。\n$\n· 只需經手機或電腦登記及登入myPrudential,在\n發生事故後的31天內,上載數份所需索償表格\n及文件,就能申請電子索償,不但隨時隨地查閱\n索償狀態,日後更可輕鬆查閱保單詳情。\nConfidential\n41\n此為機密文件,及只作內部業務用途。請勿轉發。\n請注意:整個銷售過程及所有申請程序必須在香港進行保誠精選「家居寶」2022\n12. 索償\n12.2 索償項目\n12.2.1 家居財物/個人財物失竊保障\n■ 必須於發現後二十四小時內向警方報告\n■ 日常隨身攜帶的個人財物,不應無人看管,否則該損失可能不獲保障\n■ 請保存原有配件、使用指南、說明書及保證書,並在有需要時提供作檢\n查之用,直至索償完成\n■ 手提電話/任何具手提電話功能的電子產品,及其所有配件均不受保障\n12.2.2 滲水至第三者單單位情況\n▪\n在滲水出現時,就受保人可能需要負上的法律責任,即因疏忽而導致第\n三者損失,作出處理及賠償\n■ 當發現滲水,不論第三者有否追討賠償,受保人都應立即填寫索償表格\n並交予我們作通知,在得悉有關情況後,我們將為賠償事宜作出考慮與\n安排\n■ 受保人應立即找出滲水的源頭,及在有需要時安排維修人員維修\n■ 如收到索償信、律師信或法庭傳票等,請勿私自回覆,並應立即交予我\n們\n■ 請勿私自向任何第三者承認責任或作出賠償承諾\n■ 如第三者向受保人追討賠償,請要求第三者以書面形式列明其要求。當\n受保人收到第三者的書面索償,請立即交予我們。如有需要,我們將直\n接聯絡第三者\n12.2.3 遺失現金及信用卡被盜用保障\n■ 若遺失信用卡,請即通知信用卡發行機構\n■ 必須於發現後二十四小時內向警方報告\nConfidential 42\n此為機密文件,及只作內部業務用途。請勿轉發。\n請注意:整個銷售過程及所有申請程序必須在香港進行",
          "content_tc": "保誠精選「家居寶」2022\n12. 索償\n12.1 客戶可經 eClaims申請索償。\n$\n· 只需經手機或電腦登記及登入myPrudential,在\n發生事故後的31天內,上載數份所需索償表格\n及文件,就能申請電子索償,不但隨時隨地查閱\n索償狀態,日後更可輕鬆查閱保單詳情。\nConfidential\n41\n此為機密文件,及只作內部業務用途。請勿轉發。\n請注意:整個銷售過程及所有申請程序必須在香港進行保誠精選「家居寶」2022\n12. 索償\n12.2 索償項目\n12.2.1 家居財物/個人財物失竊保障\n■ 必須於發現後二十四小時內向警方報告\n■ 日常隨身攜帶的個人財物,不應無人看管,否則該損失可能不獲保障\n■ 請保存原有配件、使用指南、說明書及保證書,並在有需要時提供作檢\n查之用,直至索償完成\n■ 手提電話/任何具手提電話功能的電子產品,及其所有配件均不受保障\n12.2.2 滲水至第三者單單位情況\n▪\n在滲水出現時,就受保人可能需要負上的法律責任,即因疏忽而導致第\n三者損失,作出處理及賠償\n■ 當發現滲水,不論第三者有否追討賠償,受保人都應立即填寫索償表格\n並交予我們作通知,在得悉有關情況後,我們將為賠償事宜作出考慮與\n安排\n■ 受保人應立即找出滲水的源頭,及在有需要時安排維修人員維修\n■ 如收到索償信、律師信或法庭傳票等,請勿私自回覆,並應立即交予我\n們\n■ 請勿私自向任何第三者承認責任或作出賠償承諾\n■ 如第三者向受保人追討賠償,請要求第三者以書面形式列明其要求。當\n受保人收到第三者的書面索償,請立即交予我們。如有需要,我們將直\n接聯絡第三者\n12.2.3 遺失現金及信用卡被盜用保障\n■ 若遺失信用卡,請即通知信用卡發行機構\n■ 必須於發現後二十四小時內向警方報告\nConfidential 42\n此為機密文件,及只作內部業務用途。請勿轉發。\n請注意:整個銷售過程及所有申請程序必須在香港進行",
          "filename": "Home_Sales Toolkit_26 April 2022.pdf",
          "page_number": null,
          "score": 17.685562,
          "content_chunk": ""
        },
        {
          "id": "GI000061",
          "document_id": "GI000061",
          "title_name_en": "PRUchoice Home",
          "title_name_tc": "保誠精選「家居寶」",
          "content_en": "誠精選「家居寶」?\n保單之「標準保障」〔Basic Cover〕,只合適於香港受保地址\n答\n內及整年居住的投保人,便可申請投保。\n而自選保障項目之「樓宇結構保障」〔Building Structure〕,\n必須該由受保地址之業主才可投保。\n4. 問\n如何計算樓宇面積?\n答\n若樓宇包括露台,是需要計算於受保住所內的面積。\n若樓宇包括花園、天台或平台,則不需計算於住所面積。\n5. 問\n兩間雙連單位的樓宇,打通為一間。可否購買一張保單?\n答\n可以,惟有關雙連單位打通項目,必須經屋宇署審批及按照打通\n後的總面積來購買保單。\n主要保障客戶在個人住宅之全面家居保險,保障家居因意外如颱\n風、火災、盜竊或水浸招致的家居財物損失及維修費用、因疏忽\n而引致第三者的法律責任,及特別保障在您及住戶身份下的額外\n風險。\n保障計劃分別為「小康之家」及「卓爾之家」,保費計算可以選\n擇以建築面積或實用面積投保或計算保費,保障項目及賠償額的\n詳情,請參閱「保障一覽表、保障範圍快覽及注意事項」。\nConfidential\n19\n此為機密文件,及只作內部業務用途。請勿轉發。\n請注意:整個銷售過程及所有申請程序必須在香港進行保誠精選「家居寶」2022\n33\n8. 常見問題\n保障範圍\n6.\n問\n受保住所的露台、花園,天台或平台是否屬於保障範圍?\n這些地方屬於保障範圍,並在「第三者法律責任保障」項目提供\n保障,而放在戶外家居用品或電器,因意外及損毀,可根據「家\n居財物保障之戶外家居用品額外保障」中,獲得保障。\n答\n7.\n問\n保單是否有「免責期」?\n就香港天文台已發出8號或以上警告信號的熱帶氣旋,本保單由\n答\n其原起保生效日計的首3天設有等候期,在此期間內不會就該熱\n帶氣旋所引致的損毀或損失作出賠償。\n8.\n問\n於「額外個人財物保障」項目,若財物是他人贈送而並沒有收據,\n可否購買此項保障?\n答\n一般不可以,但客户可透過獨立的評估員估值。\n有關價值証明亦可當作收據看待。\n9.\n問\n如何計算「樓宇結構保障」之保額?\n一般來說,保險公司會讓買家選擇以「物業重建費用」、「按揭\n貸款額」、或「尚餘按揭貸款額」來計算投保額。而此項投保額\n設定最低為港幣$500,000,以下3項為最常見的情況:\n1. 新業主\n當新業主到銀行申請按揭時,銀行會要求業主購買的最低火險投\n保額,一般與按揭貸款額相同。\n2.完成供款的業主\n答\n已完成供款的業主不必再因按揭要求而購買火險。不過業主可以\n繼續購買火險,以保障因火災等指明火險引致樓宇結構的損毀。\n火險投保額一般以物業重建費用釐訂,客戶可從各大地產商網站\n查看現時樓價,再用大約5-6成樓價釐訂投保額。\n3. 需續保的業主\n當收到銀行續保信時,信內會提及尚餘按揭貸款額\n(Outstanding loan amount)。此時銀行要求的火險最低續保\n投保額則最少相等於尚餘按揭貸款額。\nConfidential\n20\n此為機密文件,及只作內部業務用途。請勿轉發。\n請注意:整個銷售過程及所有申請程序必須在香港進行",
          "content_tc": "誠精選「家居寶」?\n保單之「標準保障」〔Basic Cover〕,只合適於香港受保地址\n答\n內及整年居住的投保人,便可申請投保。\n而自選保障項目之「樓宇結構保障」〔Building Structure〕,\n必須該由受保地址之業主才可投保。\n4. 問\n如何計算樓宇面積?\n答\n若樓宇包括露台,是需要計算於受保住所內的面積。\n若樓宇包括花園、天台或平台,則不需計算於住所面積。\n5. 問\n兩間雙連單位的樓宇,打通為一間。可否購買一張保單?\n答\n可以,惟有關雙連單位打通項目,必須經屋宇署審批及按照打通\n後的總面積來購買保單。\n主要保障客戶在個人住宅之全面家居保險,保障家居因意外如颱\n風、火災、盜竊或水浸招致的家居財物損失及維修費用、因疏忽\n而引致第三者的法律責任,及特別保障在您及住戶身份下的額外\n風險。\n保障計劃分別為「小康之家」及「卓爾之家」,保費計算可以選\n擇以建築面積或實用面積投保或計算保費,保障項目及賠償額的\n詳情,請參閱「保障一覽表、保障範圍快覽及注意事項」。\nConfidential\n19\n此為機密文件,及只作內部業務用途。請勿轉發。\n請注意:整個銷售過程及所有申請程序必須在香港進行保誠精選「家居寶」2022\n33\n8. 常見問題\n保障範圍\n6.\n問\n受保住所的露台、花園,天台或平台是否屬於保障範圍?\n這些地方屬於保障範圍,並在「第三者法律責任保障」項目提供\n保障,而放在戶外家居用品或電器,因意外及損毀,可根據「家\n居財物保障之戶外家居用品額外保障」中,獲得保障。\n答\n7.\n問\n保單是否有「免責期」?\n就香港天文台已發出8號或以上警告信號的熱帶氣旋,本保單由\n答\n其原起保生效日計的首3天設有等候期,在此期間內不會就該熱\n帶氣旋所引致的損毀或損失作出賠償。\n8.\n問\n於「額外個人財物保障」項目,若財物是他人贈送而並沒有收據,\n可否購買此項保障?\n答\n一般不可以,但客户可透過獨立的評估員估值。\n有關價值証明亦可當作收據看待。\n9.\n問\n如何計算「樓宇結構保障」之保額?\n一般來說,保險公司會讓買家選擇以「物業重建費用」、「按揭\n貸款額」、或「尚餘按揭貸款額」來計算投保額。而此項投保額\n設定最低為港幣$500,000,以下3項為最常見的情況:\n1. 新業主\n當新業主到銀行申請按揭時,銀行會要求業主購買的最低火險投\n保額,一般與按揭貸款額相同。\n2.完成供款的業主\n答\n已完成供款的業主不必再因按揭要求而購買火險。不過業主可以\n繼續購買火險,以保障因火災等指明火險引致樓宇結構的損毀。\n火險投保額一般以物業重建費用釐訂,客戶可從各大地產商網站\n查看現時樓價,再用大約5-6成樓價釐訂投保額。\n3. 需續保的業主\n當收到銀行續保信時,信內會提及尚餘按揭貸款額\n(Outstanding loan amount)。此時銀行要求的火險最低續保\n投保額則最少相等於尚餘按揭貸款額。\nConfidential\n20\n此為機密文件,及只作內部業務用途。請勿轉發。\n請注意:整個銷售過程及所有申請程序必須在香港進行",
          "filename": "Home_Sales Toolkit_26 April 2022.pdf",
          "page_number": null,
          "score": 17.076977,
          "content_chunk": ""
        }
      ]
    }
  ]
}